Workbook

Sheet README

Sheet Dashboard
A1: ROLLS-ROYCE VALUATION DASHBOARD
A2: Historical performance, operating forecast and valuation summary | £m unless stated | P2: Scenario | Q2: Value / Share
P3: Bear | Q3: =Sensitivity!B79 -> 6.5707899
A4: REFERENCE SHARE PRICE | E4: DCF VALUE / SHARE | I4: COMPS VALUE / SHARE | M4: DCF DOWNSIDE | P4: Base | Q4: =Sensitivity!C79 -> 8.1953525
A5: =DCF!$B$65 -> 14.45 | E5: =DCF!$B$64 -> 8.1953525 | I5: =Comparable_Companies!$B$39 -> 9.2730323 | M5: =DCF!$B$66 -> -0.43284758 | P5: Bull | Q5: =Sensitivity!D79 -> 10.431344
P6: Market Price | Q6: =DCF!B65 -> 14.45
A8: DCF ASSUMPTIONS | H8: SCENARIO VALUATION
A9: WACC | B9: =DCF!$B$26 -> 0.096193991 | H9: Scenario | I9: Bear | J9: Base | K9: Bull | P9: Year | Q9: EBIT Margin | S9: Year | T9: UFCF (£m)
A10: Terminal Growth | B10: =DCF!$B$27 -> 0.025 | H10: Value / Share | I10: =Sensitivity!B79 -> 6.5707899 | J10: =Sensitivity!C79 -> 8.1953525 | K10: =Sensitivity!D79 -> 10.431344 | P10: =Ratio_Analysis!G3 -> FY2021 | Q10: =Ratio_Analysis!G7 -> 0.03781858 | S10: =Forecast_Model!C2 -> FY2026E | T10: =Forecast_Model!C28 -> 4006.9847
A11: Net Cash (£m) | B11: =DCF!$B$61 -> 2136 | H11: Upside / (Downside) | I11: =Sensitivity!B80 -> -0.54527405 | J11: =Sensitivity!C80 -> -0.43284758 | K11: =Sensitivity!D80 -> -0.27810766 | P11: =Ratio_Analysis!H3 -> FY2022 | Q11: =Ratio_Analysis!H7 -> 0.05137499 | S11: =Forecast_Model!D2 -> FY2027E | T11: =Forecast_Model!D28 -> 4151.4341
A12: Terminal Value / EV | B12: =DCF!$B$73 -> 0.7463842 | P12: =Ratio_Analysis!I$3 -> FY2023 | Q12: =Ratio_Analysis!I7 -> 0.10318645 | S12: =Forecast_Model!E2 -> FY2028E | T12: =Forecast_Model!E28 -> 4557.8525
P13: =Ratio_Analysis!J$3 -> FY2024 | Q13: =Ratio_Analysis!J7 -> 0.13805468 | S13: =Forecast_Model!F2 -> FY2029E | T13: =Forecast_Model!F28 -> 4915.6129
P14: =Ratio_Analysis!K$3 -> FY2025 | Q14: =Ratio_Analysis!K7 -> 0.17259086 | S14: =Forecast_Model!G2 -> FY2030E | T14: =Forecast_Model!G28 -> 5207.4202
A15: VALUATION SUMMARY | H15: OPERATING FORECAST | P15: =Forecast_Model!C2 -> FY2026E | Q15: =Forecast_Model!C18 -> 0.20594275
A16: Method | B16: Value / Share | C16: Upside / (Downside) | I16: =Forecast_Model!B2 -> FY2025A | J16: =Forecast_Model!C2 -> FY2026E | K16: =Forecast_Model!D2 -> FY2027E | L16: =Forecast_Model!E2 -> FY2028E | M16: =Forecast_Model!F2 -> FY2029E | N16: =Forecast_Model!G2 -> FY2030E | P16: =Forecast_Model!D2 -> FY2027E | Q16: =Forecast_Model!D18 -> 0.1906332
A17: DCF | B17: =DCF!$B$64 -> 8.1953525 | C17: =DCF!$B$66 -> -0.43284758 | H17: Revenue (£m) | I17: =Forecast_Model!B9 -> 20059 | J17: =Forecast_Model!C9 -> 23684.547 | K17: =Forecast_Model!D9 -> 26325.011 | L17: =Forecast_Model!E9 -> 28811.767 | M17: =Forecast_Model!F9 -> 31037.626 | N17: =Forecast_Model!G9 -> 32905.412 | P17: =Forecast_Model!E2 -> FY2028E | Q17: =Forecast_Model!E18 -> 0.19129306
A18: Trading Comps | B18: =Comparable_Companies!$B$39 -> 9.2730323 | C18: =Comparable_Companies!$B$40 -> -0.35826766 | H18: Operating Profit (£m) | I18: =Forecast_Model!B17 -> 3462 | J18: =Forecast_Model!C17 -> 4877.6608 | K18: =Forecast_Model!D17 -> 5018.4212 | L18: =Forecast_Model!E17 -> 5511.4913 | M18: =Forecast_Model!F17 -> 5944.8061 | N18: =Forecast_Model!G17 -> 6297.2133 | P18: =Forecast_Model!F2 -> FY2029E | Q18: =Forecast_Model!F18 -> 0.19153547
A19: Reference Price | B19: =DCF!$B$65 -> 14.45 | H19: EBIT Margin | I19: =Forecast_Model!B18 -> 0.17259086 | J19: =Forecast_Model!C18 -> 0.20594275 | K19: =Forecast_Model!D18 -> 0.1906332 | L19: =Forecast_Model!E18 -> 0.19129306 | M19: =Forecast_Model!F18 -> 0.19153547 | N19: =Forecast_Model!G18 -> 0.19137318 | P19: =Forecast_Model!G2 -> FY2030E | Q19: =Forecast_Model!G18 -> 0.19137318
A22: SEGMENT REVENUE OUTLOOK
B23: =Forecast_Model!B2 -> FY2025A | C23: =Forecast_Model!C2 -> FY2026E | D23: =Forecast_Model!D2 -> FY2027E | E23: =Forecast_Model!E2 -> FY2028E | F23: =Forecast_Model!F2 -> FY2029E | G23: =Forecast_Model!G2 -> FY2030E | I23: KEY VALUATION TAKEAWAYS
A24: Civil Aerospace | B24: =Operating_Drivers!K5 -> 10382 | C24: =Operating_Drivers!L5 -> 12612.734 | D24: =Operating_Drivers!M5 -> 14154.697 | E24: =Operating_Drivers!N5 -> 15514.363 | F24: =Operating_Drivers!O5 -> 16598.208 | G24: =Operating_Drivers!P5 -> 17322.951 | I24: DCF valuation remains materially below the reference market price.
A25: Defence | B25: =Operating_Drivers!K8 -> 4772 | C25: =Operating_Drivers!L8 -> 5255.6288 | D25: =Operating_Drivers!M8 -> 5717.2943 | E25: =Operating_Drivers!N8 -> 6222.386 | F25: =Operating_Drivers!O8 -> 6775.2261 | G25: =Operating_Drivers!P8 -> 7380.5883
A26: Power Systems | B26: =Operating_Drivers!K11 -> 4892 | C26: =Operating_Drivers!L11 -> 5804.1844 | D26: =Operating_Drivers!M11 -> 6441.0197 | E26: =Operating_Drivers!N11 -> 7063.0183 | F26: =Operating_Drivers!O11 -> 7652.1919 | G26: =Operating_Drivers!P11 -> 8189.8732 | I26: Trading comparables imply a higher value than the DCF, but remain below market.
I28: Even the Bull operating scenario does not fully justify the reference share price.

Sheet Historical_FS
A1: Rolls-Royce Holdings plc| Historical Financials
A2: All figures in £m, unless stated otherwise | Year ended 31 December
B4: FY2016 | C4: FY2017 | D4: FY2018 | E4: FY2019 | F4: FY2020 | G4: FY2021 | H4: FY2022 | I4: FY2023 | J4: FY2024 | K4: FY2025 | L4: FY2026E | M4: FY2027E | N4: FY2028E | O4: FY2029E | P4: FY2030E
A6: INCOME STATEMENT
A7: Underlying Revenue | B7: 13783 | C7: 13671 | D7: 15067 | E7: 15450 | F7: 11430 | G7: 10947 | H7: 12691 | I7: 15409 | J7: 17848 | K7: 20059
A8: Reported Revenue | B8: 14955 | C8: 14747 | D8: 15729 | E8: 16587 | F8: 11491 | G8: 11218 | H8: 13520 | I8: 16486 | J8: =Raw_Data!$AK$4 -> 18909 | K8: =Raw_Data!$AJ$4 -> 21207
A9: YoY Underlying Revenue Growth % | C9: N/M | D9: =D7/C7-1 -> 0.10211396 | E9: =IFERROR(E7/D7-1,"") -> 0.025419792 | F9: =IFERROR(F7/E7-1,"") -> -0.26019417 | G9: =IFERROR(G7/F7-1,"") -> -0.042257218 | H9: =IFERROR(H7/G7-1,"") -> 0.15931305 | I9: =IFERROR(I7/H7-1,"") -> 0.21416752 | J9: =IFERROR(J7/I7-1,"") -> 0.15828412 | K9: =IFERROR(K7/J7-1,"") -> 0.12387943
A10: Underlying Operating Profit | B10: 915 | C10: 306 | D10: 616 | E10: 808 | F10: -2008 | G10: 414 | H10: 652 | I10: 1590 | J10: 2464 | K10: 3462
A11: Underlying EBIT Margin % | B11: =IFERROR(B10/B7,"") -> 0.066386128 | C11: =IFERROR(C10/C7,"") -> 0.022383147 | D11: =IFERROR(D10/D7,"") -> 0.040884051 | E11: =IFERROR(E10/E7,"") -> 0.052297735 | F11: =IFERROR(F10/F7,"") -> -0.17567804 | G11: =IFERROR(G10/G7,"") -> 0.03781858 | H11: =IFERROR(H10/H7,"") -> 0.05137499 | I11: =IFERROR(I10/I7,"") -> 0.10318645 | ... K11: =IFERROR(K10/K7,"") -> 0.17259086
A12: Reported Operating Profit | B12: 44 | C12: 366 | D12: -1161 | E12: -852 | F12: -1972 | G12: 513 | H12: 837 | I12: 1944 | J12: =Raw_Data!$AK$5 -> 2906 | K12: =Raw_Data!$AJ$5 -> 4468
A13: Gain / (Loss) on Disposal of Businesses | B13: -3 | C13: 785 | D13: 358 | E13: 139 | F13: -14 | G13: 56 | H13: 81 | I13: 1 | J13: =Raw_Data!$AK6 -> 16 | K13: =Raw_Data!$AJ6 -> 809
A14: Reported EBIT Margin % | B14: =IFERROR(B12/B8,"") -> 0.0029421598 | C14: =C12/C8 -> 0.024818607 | D14: =D12/D8 -> -0.073812703 | E14: =E12/E8 -> -0.051365527 | F14: =F12/F8 -> -0.17161257 | G14: =G12/G8 -> 0.045730077 | H14: =H12/H8 -> 0.061908284 | I14: =I12/I8 -> 0.11791823 | J14: =J12/J8 -> 0.15368343 | K14: =K12/K8 -> 0.21068515
A15: Net Financing Income / (Cost) | B15: -4677 | C15: 2747 | D15: -2144 | E15: -178 | F15: -813 | G15: -863 | H15: -2420 | I15: 482 | J15: =Raw_Data!$AK$7 -> -688 | K15: =Raw_Data!$AJ$7 -> 1658
A16: Profit Before Tax | B16: -4636 | C16: 3898 | D16: -2947 | E16: -891 | F16: -2799 | G16: -294 | H16: -1502 | I16: 2427 | J16: =Raw_Data!$AK$8 -> 2234 | K16: =Raw_Data!$AJ$8 -> 6935
A17: Taxation (Charge) / Credit | B17: 604 | C17: -515 | D17: -554 | E17: -420 | F17: -302 | G17: 418 | H17: 308 | I17: -23 | J17: =Raw_Data!$AK$9 -> 250 | K17: =Raw_Data!$AJ$9 -> -1099
A18: Effective Tax Rate % | B18: =-B17/B16 -> 0.13028473 | C18: =-C17/C16 -> 0.13211904 | D18: =-D17/D16 -> -0.18798778 | E18: =-E17/E16 -> -0.47138047 | F18: =-F17/F16 -> -0.10789568 | G18: =-G17/G16 -> 1.4217687 | H18: =-H17/H16 -> 0.20505992 | I18: =-I17/I16 -> 0.0094767202 | ... K18: =-K17/K16 -> 0.15847152
A19: Net Income Attributable to Ordinary Shareholders | B19: -4032 | C19: 3382 | D19: -2401 | E19: -1315 | F19: -3101 | G19: 123 | H19: -1189 | I19: 2412 | J19: =Raw_Data!$AK$10 -> 2521 | K19: =Raw_Data!$AJ$10 -> 5841
A20: Diluted EPS (p) | B20: -220.08 | C20: 183.8 | D20: -129.15 | E20: -69.07 | F20: -51.81 | G20: 1.47 | H20: -14.24 | I20: 28.7 | J20: 29.87 | K20: 69.14
A22: CASH FLOW / FCF
A23: Depreciation, Amortisation & Impairment (Funds Flow Basis) | B23: 720 | C23: 652 | D23: 756 | E23: 1068 | F23: 1048 | G23: 971 | H23: 953 | I23: 978 | J23: 853 | K23: 900
A24: Capital Expenditure (PPE + Intangibles) | B24: -1201 | C24: -1377 | D24: -1585 | E24: -1338 | F24: -895 | G24: -496 | H24: -504 | I24: -695 | J24: -876 | K24: -978
A25: Working Capital Cash Impact | B25: -55 | C25: -219 | D25: 581 | E25: 531 | F25: -1527 | G25: -810 | H25: -524 | I25: -356 | J25: 280 | K25: 421
A26: Cash Tax Paid | B26: -157 | C26: -180 | D26: -248 | E26: -175 | F26: -231 | G26: -185 | H26: -174 | I26: -172 | J26: -381 | K26: -555
A27: Company-Reported Free Cash Flow | B27: 100 | C27: 259 | D27: 568 | E27: 873 | F27: -4255 | G27: -1485 | H27: 505 | I27: 1285 | J27: 2425 | K27: 3270
A28: FCF Margin % | B28: =B27/B7 -> 0.0072553145 | C28: =C27/C7 -> 0.018945212 | D28: =D27/D7 -> 0.037698281 | E28: =E27/E7 -> 0.056504854 | F28: =F27/F7 -> -0.37226597 | G28: =G27/G7 -> -0.1356536 | H28: =H27/H7 -> 0.039791979 | I28: =I27/I7 -> 0.083392822 | ... K28: =K27/K7 -> 0.16301909
A30: BALANCE SHEET / VALUATION
A31: Cash and Cash Equivalents (Balance Sheet) | B31: 2771 | C31: 2953 | D31: 4974 | E31: 4443 | F31: 3452 | G31: 2621 | H31: 2607 | I31: 3784 | J31: =Raw_Data!$AK$12 -> 5575 | K31: =Raw_Data!$AJ$12 -> 6244
A32: Gross Borrowings (Excluding Lease Liabilities) | B32: 3357 | C32: 3488 | D32: 4411 | E32: 3331 | F32: 5280 | G32: 6032 | H32: 4108 | I32: 4046 | J32: 3575 | K32: 2799
A33: Net Debt / (Net Cash) | B33: 225 | C33: 305 | D33: -611 | E33: 993 | F33: 3576 | G33: 5157 | H33: 3251 | I33: 1952 | J33: -475 | K33: -1895
A34: Diluted Weighted-Average Shares (m) | B34: 1832 | C34: 1840 | D34: 1859 | E34: 1904 | F34: 5985 | G34: 8352 | H34: 8332 | I34: 8405 | J34: 8439 | K34: 8448
A36: SEGMENT REVENUE
A37: Civil Aerospace Revenue | B37: 7067 | C37: 6598 | D37: 7378 | E37: 8107 | F37: 5068 | G37: 4536 | H37: 5686 | I37: 7348 | J37: 9040 | K37: 10382
A38: Defence Revenue | B38: 2209 | C38: 3180 | D38: 3124 | E38: 3250 | F38: 3355 | G38: 3368 | H38: 3660 | I38: 4077 | J38: 4522 | K38: 4772
A39: Power Systems Revenue | B39: 2655 | C39: 3008 | D39: 3434 | E39: 3545 | F39: 2735 | G39: 2749 | H39: 3347 | I39: 3968 | J39: 4271 | K39: 4892
A40: Other / Legacy / New Markets Revenue | B40: =B42-SUM(B37:B39)-B41 -> 1928 | C40: =C42-SUM(C37:C39)-C41 -> 885 | D40: =D42-SUM(D37:D39)-D41 -> 1560 | E40: =E42-SUM(E37:E39)-E41 -> 1125 | F40: =F42-SUM(F37:F39)-F41 -> 278 | G40: =G42-SUM(G37:G39)-G41 -> 305 | H40: =H42-SUM(H37:H39)-H41 -> 3 | I40: =I42-SUM(I37:I39)-I41 -> 16 | ... K40: =K42-SUM(K37:K39)-K41 -> 13
A41: Inter-segment / Eliminations | B41: -76 | C41: 0 | D41: -429 | E41: -577 | F41: -6 | G41: -11 | H41: -5 | I41: 0 | J41: 0 | K41: 0
A42: Group Underlying Revenue | B42: =B7 -> 13783 | C42: =C7 -> 13671 | D42: =D7 -> 15067 | E42: =E7 -> 15450 | F42: =F7 -> 11430 | G42: =G7 -> 10947 | H42: =H7 -> 12691 | I42: =I7 -> 15409 | ... K42: =K7 -> 20059
A43: Segment Revenue Reconciliation Check | B43: =B42-SUM(B37:B41) -> 0 | C43: =C42-SUM(C37:C41) -> 0 | D43: =D42-SUM(D37:D41) -> 0 | E43: =E42-SUM(E37:E41) -> 0 | F43: =F42-SUM(F37:F41) -> 0 | G43: =G42-SUM(G37:G41) -> 0 | H43: =H42-SUM(H37:H41) -> 0 | I43: =I42-SUM(I37:I41) -> 0 | ... K43: =K42-SUM(K37:K41) -> 0
A45: SEGMENT PROFITABILITY
A46: Civil Aerospace Operating Profit | B46: 367 | C46: -343 | D46: -162 | E46: 44 | F46: -2535 | G46: -172 | H46: 143 | I46: 850 | J46: 1505 | K46: 2130
A47: Civil Aerospace Margin % | B47: =B46/B37 -> 0.051931513 | C47: =C46/C37 -> -0.05198545 | D47: =D46/D37 -> -0.02195717 | E47: =E46/E37 -> 0.0054274084 | F47: =F46/F37 -> -0.50019732 | G47: =G46/G37 -> -0.037918871 | H47: =H46/H37 -> 0.02514949 | I47: =I46/I37 -> 0.11567774 | ... K47: =K46/K37 -> 0.20516278
A48: Defence Operating Profit | B48: 384 | C48: 454 | D48: 427 | E48: 415 | F48: 461 | G48: 457 | H48: 432 | I48: 562 | J48: 644 | K48: 689
A49: Defence Margin % | B49: =B48/B38 -> 0.17383431 | C49: =C48/C38 -> 0.1427673 | D49: =D48/D38 -> 0.13668374 | E49: =E48/E38 -> 0.12769231 | F49: =F48/F38 -> 0.13740686 | G49: =G48/G38 -> 0.13568884 | H49: =H48/H38 -> 0.11803279 | I49: =I48/I38 -> 0.13784646 | ... K49: =K48/K38 -> 0.14438391
A50: Power Systems Operating Profit | B50: 191 | C50: 261 | D50: 315 | E50: 367 | F50: 188 | G50: 242 | H50: 281 | I50: 413 | J50: 560 | K50: 852
A51: Power Systems Margin % | B51: =B50/B39 -> 0.071939736 | C51: =C50/C39 -> 0.086768617 | D51: =D50/D39 -> 0.091729761 | E51: =E50/E39 -> 0.10352609 | F51: =F50/F39 -> 0.068738574 | G51: =G50/G39 -> 0.088032012 | H51: =H50/H39 -> 0.083955781 | I51: =I50/I39 -> 0.10408266 | ... K51: =K50/K39 -> 0.1741619
A52: Other / Corporate Operating Profit/(Loss) | B52: =B10-B46-B48-B50 -> -27 | C52: =C10-C46-C48-C50 -> -66 | D52: =D10-D46-D48-D50 -> 36 | E52: =E10-E46-E48-E50 -> -18 | F52: =F10-F46-F48-F50 -> -122 | G52: =G10-G46-G48-G50 -> -113 | H52: =H10-H46-H48-H50 -> -204 | I52: =I10-I46-I48-I50 -> -235 | ... K52: =K10-K46-K48-K50 -> -209

Sheet Ratio_Analysis
A1: ROLLS-ROYCE HISTORICAL RATIO ANALYSIS
A2: All ratios based on historical reported / underlying financial data
B3: =Historical_FS!B4 -> FY2016 | C3: =Historical_FS!C4 -> FY2017 | D3: =Historical_FS!D4 -> FY2018 | E3: =Historical_FS!E4 -> FY2019 | F3: =Historical_FS!F4 -> FY2020 | G3: =Historical_FS!G4 -> FY2021 | H3: =Historical_FS!H4 -> FY2022 | I3: =Historical_FS!I4 -> FY2023 | ... K3: =Historical_FS!K4 -> FY2025
A5: OPERATING & CASH FLOW RATIOS
A6: Underlying Revenue Growth % | B6: =Historical_FS!B9 -> 0 | C6: =Historical_FS!C9 -> N/M | D6: =Historical_FS!D9 -> 0.10211396 | E6: =Historical_FS!E9 -> 0.025419792 | F6: =Historical_FS!F9 -> -0.26019417 | G6: =Historical_FS!G9 -> -0.042257218 | H6: =Historical_FS!H9 -> 0.15931305 | I6: =Historical_FS!I9 -> 0.21416752 | ... K6: =Historical_FS!K9 -> 0.12387943
A7: Underlying EBIT Margin % | B7: =Historical_FS!B11 -> 0.066386128 | C7: =Historical_FS!C11 -> 0.022383147 | D7: =Historical_FS!D11 -> 0.040884051 | E7: =Historical_FS!E11 -> 0.052297735 | F7: =Historical_FS!F11 -> -0.17567804 | G7: =Historical_FS!G11 -> 0.03781858 | H7: =Historical_FS!H11 -> 0.05137499 | I7: =Historical_FS!I11 -> 0.10318645 | ... K7: =Historical_FS!K11 -> 0.17259086
A8: Reported EBIT Margin % | B8: =Historical_FS!B14 -> 0.0029421598 | C8: =Historical_FS!C14 -> 0.024818607 | D8: =Historical_FS!D14 -> -0.073812703 | E8: =Historical_FS!E14 -> -0.051365527 | F8: =Historical_FS!F14 -> -0.17161257 | G8: =Historical_FS!G14 -> 0.045730077 | H8: =Historical_FS!H14 -> 0.061908284 | I8: =Historical_FS!I14 -> 0.11791823 | ... K8: =Historical_FS!K14 -> 0.21068515
A9: Effective Tax Rate % | B9: =Historical_FS!B18 -> 0.13028473 | C9: =Historical_FS!C18 -> 0.13211904 | D9: =Historical_FS!D18 -> -0.18798778 | E9: =Historical_FS!E18 -> -0.47138047 | F9: =Historical_FS!F18 -> -0.10789568 | G9: =Historical_FS!G18 -> 1.4217687 | H9: =Historical_FS!H18 -> 0.20505992 | I9: =Historical_FS!I18 -> 0.0094767202 | ... K9: =Historical_FS!K18 -> 0.15847152
A10: Free Cash Flow Margin % | B10: =Historical_FS!B28 -> 0.0072553145 | C10: =Historical_FS!C28 -> 0.018945212 | D10: =Historical_FS!D28 -> 0.037698281 | E10: =Historical_FS!E28 -> 0.056504854 | F10: =Historical_FS!F28 -> -0.37226597 | G10: =Historical_FS!G28 -> -0.1356536 | H10: =Historical_FS!H28 -> 0.039791979 | I10: =Historical_FS!I28 -> 0.083392822 | ... K10: =Historical_FS!K28 -> 0.16301909
A12: CASH FLOW / CAPITAL INTENSITY
A13: D&A / Revenue % | B13: =Historical_FS!B23/Historical_FS!B7 -> 0.052238265 | C13: =Historical_FS!C23/Historical_FS!C7 -> 0.047692195 | D13: =Historical_FS!D23/Historical_FS!D7 -> 0.050175881 | E13: =Historical_FS!E23/Historical_FS!E7 -> 0.069126214 | F13: =Historical_FS!F23/Historical_FS!F7 -> 0.091688539 | G13: =Historical_FS!G23/Historical_FS!G7 -> 0.0887001 | H13: =Historical_FS!H23/Historical_FS!H7 -> 0.075092585 | I13: =Historical_FS!I23/Historical_FS!I7 -> 0.063469401 | ... K13: =Historical_FS!K23/Historical_FS!K7 -> 0.04486764
A14: Capex / Revenue % | B14: =-Historical_FS!B24/Historical_FS!B7 -> 0.087136327 | C14: =-Historical_FS!C24/Historical_FS!C7 -> 0.10072416 | D14: =-Historical_FS!D24/Historical_FS!D7 -> 0.10519679 | E14: =-Historical_FS!E24/Historical_FS!E7 -> 0.086601942 | F14: =-Historical_FS!F24/Historical_FS!F7 -> 0.078302712 | G14: =-Historical_FS!G24/Historical_FS!G7 -> 0.045309217 | H14: =-Historical_FS!H24/Historical_FS!H7 -> 0.039713183 | I14: =-Historical_FS!I24/Historical_FS!I7 -> 0.045103511 | ... K14: =-Historical_FS!K24/Historical_FS!K7 -> 0.048756169
A15: Working Capital Cash Impact / Revenue % | B15: =Historical_FS!B25/Historical_FS!B7 -> -0.003990423 | C15: =Historical_FS!C25/Historical_FS!C7 -> -0.016019311 | D15: =Historical_FS!D25/Historical_FS!D7 -> 0.038561094 | E15: =Historical_FS!E25/Historical_FS!E7 -> 0.034368932 | F15: =Historical_FS!F25/Historical_FS!F7 -> -0.1335958 | G15: =Historical_FS!G25/Historical_FS!G7 -> -0.073992875 | H15: =Historical_FS!H25/Historical_FS!H7 -> -0.041289103 | I15: =Historical_FS!I25/Historical_FS!I7 -> -0.023103381 | ... K15: =Historical_FS!K25/Historical_FS!K7 -> 0.020988085
A16: Cash Tax Paid / Revenue % | B16: =-Historical_FS!B26/Historical_FS!B7 -> 0.011390844 | C16: =-Historical_FS!C26/Historical_FS!C7 -> 0.013166557 | D16: =-Historical_FS!D26/Historical_FS!D7 -> 0.016459813 | E16: =-Historical_FS!E26/Historical_FS!E7 -> 0.011326861 | F16: =-Historical_FS!F26/Historical_FS!F7 -> 0.020209974 | G16: =-Historical_FS!G26/Historical_FS!G7 -> 0.016899607 | H16: =-Historical_FS!H26/Historical_FS!H7 -> 0.013710504 | I16: =-Historical_FS!I26/Historical_FS!I7 -> 0.011162308 | ... K16: =-Historical_FS!K26/Historical_FS!K7 -> 0.027668378
A18: BALANCE SHEET / LEVERAGE
A19: Gross Borrowings / Revenue % | B19: =Historical_FS!B32/Historical_FS!B7 -> 0.24356091 | C19: =Historical_FS!C32/Historical_FS!C7 -> 0.25513861 | D19: =Historical_FS!D32/Historical_FS!D7 -> 0.29275901 | E19: =Historical_FS!E32/Historical_FS!E7 -> 0.21559871 | F19: =Historical_FS!F32/Historical_FS!F7 -> 0.46194226 | G19: =Historical_FS!G32/Historical_FS!G7 -> 0.55101854 | H19: =Historical_FS!H32/Historical_FS!H7 -> 0.32369396 | I19: =Historical_FS!I32/Historical_FS!I7 -> 0.26257382 | ... K19: =Historical_FS!K32/Historical_FS!K7 -> 0.13953836
A20: Net Debt / (Net Cash) / Revenue % | B20: =Historical_FS!B33/Historical_FS!B7 -> 0.016324458 | C20: =Historical_FS!C33/Historical_FS!C7 -> 0.022309999 | D20: =Historical_FS!D33/Historical_FS!D7 -> -0.0405522 | E20: =Historical_FS!E33/Historical_FS!E7 -> 0.064271845 | F20: =Historical_FS!F33/Historical_FS!F7 -> 0.31286089 | G20: =Historical_FS!G33/Historical_FS!G7 -> 0.47108797 | H20: =Historical_FS!H33/Historical_FS!H7 -> 0.25616579 | I20: =Historical_FS!I33/Historical_FS!I7 -> 0.12667921 | ... K20: =Historical_FS!K33/Historical_FS!K7 -> -0.09447131
A21: Cash / Revenue % | B21: =Historical_FS!B31/Historical_FS!B7 -> 0.20104477 | C21: =Historical_FS!C31/Historical_FS!C7 -> 0.21600468 | D21: =Historical_FS!D31/Historical_FS!D7 -> 0.33012544 | E21: =Historical_FS!E31/Historical_FS!E7 -> 0.28757282 | F21: =Historical_FS!F31/Historical_FS!F7 -> 0.30201225 | G21: =Historical_FS!G31/Historical_FS!G7 -> 0.23942633 | H21: =Historical_FS!H31/Historical_FS!H7 -> 0.20542116 | I21: =Historical_FS!I31/Historical_FS!I7 -> 0.24557077 | ... K21: =Historical_FS!K31/Historical_FS!K7 -> 0.31128172
A23: SEGMENT MARGINS
A24: Civil Aerospace Margin % | B24: =Historical_FS!B47 -> 0.051931513 | C24: =Historical_FS!C47 -> -0.05198545 | D24: =Historical_FS!D47 -> -0.02195717 | E24: =Historical_FS!E47 -> 0.0054274084 | F24: =Historical_FS!F47 -> -0.50019732 | G24: =Historical_FS!G47 -> -0.037918871 | H24: =Historical_FS!H47 -> 0.02514949 | I24: =Historical_FS!I47 -> 0.11567774 | ... K24: =Historical_FS!K47 -> 0.20516278
A25: Defence Margin % | B25: =Historical_FS!B49 -> 0.17383431 | C25: =Historical_FS!C49 -> 0.1427673 | D25: =Historical_FS!D49 -> 0.13668374 | E25: =Historical_FS!E49 -> 0.12769231 | F25: =Historical_FS!F49 -> 0.13740686 | G25: =Historical_FS!G49 -> 0.13568884 | H25: =Historical_FS!H49 -> 0.11803279 | I25: =Historical_FS!I49 -> 0.13784646 | ... K25: =Historical_FS!K49 -> 0.14438391
A26: Power Systems Margin % | B26: =Historical_FS!B51 -> 0.071939736 | C26: =Historical_FS!C51 -> 0.086768617 | D26: =Historical_FS!D51 -> 0.091729761 | E26: =Historical_FS!E51 -> 0.10352609 | F26: =Historical_FS!F51 -> 0.068738574 | G26: =Historical_FS!G51 -> 0.088032012 | H26: =Historical_FS!H51 -> 0.083955781 | I26: =Historical_FS!I51 -> 0.10408266 | ... K26: =Historical_FS!K51 -> 0.1741619

Sheet Operating_Drivers
A1: OPERATING DRIVERS
B2: FY2016 | C2: FY2017 | D2: FY2018 | E2: FY2019 | F2: FY2020 | G2: FY2021 | H2: FY2022 | I2: FY2023 | J2: FY2024 | K2: FY2025 | L2: FY2026E | M2: FY2027E | N2: FY2028E | O2: FY2029E | P2: FY2030E | R2: Forecast Support
R4: Metric | S4: Value
A5: Civil Aerospace Revenue | B5: =Historical_FS!B37 -> 7067 | C5: =Historical_FS!C37 -> 6598 | D5: =Historical_FS!D37 -> 7378 | E5: =Historical_FS!E37 -> 8107 | F5: =Historical_FS!F37 -> 5068 | G5: =Historical_FS!G37 -> 4536 | H5: =Historical_FS!H37 -> 5686 | I5: =Historical_FS!I37 -> 7348 | ... K5: =Historical_FS!K37 -> 10382 | L5: =$S$103 -> 12612.734 | M5: =L5*(1+M6) -> 14154.697 | N5: =M5*(1+N6) -> 15514.363 | O5: =N5*(1+O6) -> 16598.208 | P5: =O5*(1+P6) -> 17322.951 | R5: Civil Aerospace 3Y CAGR | S5: =(K5/H5)^(1/3)-1 -> 0.2222444
A6: YoY Growth % | C6: =IFERROR(C5/B5-1,"") -> -0.066364794 | D6: =IFERROR(D5/C5-1,"") -> 0.11821764 | E6: =IFERROR(E5/D5-1,"") -> 0.098807265 | F6: =IFERROR(F5/E5-1,"") -> -0.37486123 | G6: =IFERROR(G5/F5-1,"") -> -0.10497238 | H6: =IFERROR(H5/G5-1,"") -> 0.25352734 | I6: =IFERROR(I5/H5-1,"") -> 0.29229687 | J6: =IFERROR(J5/I5-1,"") -> 0.23026674 | K6: =IFERROR(K5/J5-1,"") -> 0.14845133 | L6: =L5/K5-1 -> 0.2148655 | M6: =$S$21+($S$25-$S$21)*(COLUMN()-COLUMN($L6))/4 -> 0.12225447 | N6: =$S$21+($S$25-$S$21)*(COLUMN()-COLUMN($L6))/4 -> 0.096057611 | O6: =$S$21+($S$25-$S$21)*(COLUMN()-COLUMN($L6))/4 -> 0.069860753 | P6: =$S$21+($S$25-$S$21)*(COLUMN()-COLUMN($L6))/4 -> 0.043663894 | R6: Defence 3Y CAGR | S6: =(K8/H8)^(1/3)-1 -> 0.092462278
R7: Power Systems 3Y CAGR | S7: =(K11/H11)^(1/3)-1 -> 0.13486337
A8: Defence Revenue | B8: =Historical_FS!B38 -> 2209 | C8: =Historical_FS!C38 -> 3180 | D8: =Historical_FS!D38 -> 3124 | E8: =Historical_FS!E38 -> 3250 | F8: =Historical_FS!F38 -> 3355 | G8: =Historical_FS!G38 -> 3368 | H8: =Historical_FS!H38 -> 3660 | I8: =Historical_FS!I38 -> 4077 | ... K8: =Historical_FS!K38 -> 4772 | L8: =$S$104 -> 5255.6288 | M8: =L8*(1+M9) -> 5717.2943 | N8: =M8*(1+N9) -> 6222.386 | O8: =N8*(1+O9) -> 6775.2261 | P8: =O8*(1+P9) -> 7380.5883 | R8: Group Revenue 3Y CAGR | S8: =(K17/H17)^(1/3)-1 -> 0.16485306
A9: YoY Growth % | C9: =IFERROR(C8/B8-1,"") -> 0.43956541 | D9: =IFERROR(D8/C8-1,"") -> -0.017610063 | E9: =IFERROR(E8/D8-1,"") -> 0.040332907 | F9: =IFERROR(F8/E8-1,"") -> 0.032307692 | G9: =IFERROR(G8/F8-1,"") -> 0.0038748137 | H9: =IFERROR(H8/G8-1,"") -> 0.086698337 | I9: =IFERROR(I8/H8-1,"") -> 0.11393443 | J9: =IFERROR(J8/I8-1,"") -> 0.10914888 | K9: =IFERROR(K8/J8-1,"") -> 0.055285272 | L9: =L8/K8-1 -> 0.1013472 | M9: =$S$22+($S$26-$S$22)*(COLUMN()-COLUMN($L9))/4 -> 0.087842104 | N9: =$S$22+($S$26-$S$22)*(COLUMN()-COLUMN($L9))/4 -> 0.088344529 | O9: =$S$22+($S$26-$S$22)*(COLUMN()-COLUMN($L9))/4 -> 0.088846955 | P9: =$S$22+($S$26-$S$22)*(COLUMN()-COLUMN($L9))/4 -> 0.089349381
R10: Civil FY2025 Growth | S10: =K6 -> 0.14845133
A11: Power Systems | B11: =Historical_FS!B39 -> 2655 | C11: =Historical_FS!C39 -> 3008 | D11: =Historical_FS!D39 -> 3434 | E11: =Historical_FS!E39 -> 3545 | F11: =Historical_FS!F39 -> 2735 | G11: =Historical_FS!G39 -> 2749 | H11: =Historical_FS!H39 -> 3347 | I11: =Historical_FS!I39 -> 3968 | ... K11: =Historical_FS!K39 -> 4892 | L11: =$S$105 -> 5804.1844 | M11: =L11*(1+M12) -> 6441.0197 | N11: =M11*(1+N12) -> 7063.0183 | O11: =N11*(1+O12) -> 7652.1919 | P11: =O11*(1+P12) -> 8189.8732 | R11: Defence FY2025 Growth | S11: =K9 -> 0.055285272
A12: YoY Growth % | C12: =IFERROR(C11/B11-1,"") -> 0.13295669 | D12: =IFERROR(D11/C11-1,"") -> 0.14162234 | E12: =IFERROR(E11/D11-1,"") -> 0.032323821 | F12: =IFERROR(F11/E11-1,"") -> -0.22849083 | G12: =IFERROR(G11/F11-1,"") -> 0.00511883 | H12: =IFERROR(H11/G11-1,"") -> 0.21753365 | I12: =IFERROR(I11/H11-1,"") -> 0.18553929 | J12: =IFERROR(J11/I11-1,"") -> 0.076360887 | K12: =IFERROR(K11/J11-1,"") -> 0.1453992 | L12: =L11/K11-1 -> 0.18646451 | M12: =$S$23+($S$27-$S$23)*(COLUMN()-COLUMN($L12))/4 -> 0.10972003 | N12: =$S$23+($S$27-$S$23)*(COLUMN()-COLUMN($L12))/4 -> 0.096568356 | O12: =$S$23+($S$27-$S$23)*(COLUMN()-COLUMN($L12))/4 -> 0.08341668 | P12: =$S$23+($S$27-$S$23)*(COLUMN()-COLUMN($L12))/4 -> 0.070265004 | R12: Power Systems FY2025 Growth | S12: =K12 -> 0.1453992
R13: Group FY2025 Growth | S13: =K18 -> 0.12387943
A14: Other/Legacy/New Markets Revenue | B14: =Historical_FS!B40 -> 1928 | C14: =Historical_FS!C40 -> 885 | D14: =Historical_FS!D40 -> 1560 | E14: =Historical_FS!E40 -> 1125 | F14: =Historical_FS!F40 -> 278 | G14: =Historical_FS!G40 -> 305 | H14: =Historical_FS!H40 -> 3 | I14: =Historical_FS!I40 -> 16 | ... K14: =Historical_FS!K40 -> 13 | L14: =$S$106 -> 12 | M14: =(L14*(1+M15)) -> 12 | N14: =(M14*(1+N15)) -> 12 | O14: =(N14*(1+O15)) -> 12 | P14: =(O14*(1+P15)) -> 12
A15: YoY Growth % | C15: =IFERROR(C14/B14-1,"") -> -0.5409751 | D15: =IFERROR(D14/C14-1,"") -> 0.76271186 | E15: =IFERROR(E14/D14-1,"") -> -0.27884615 | F15: =IFERROR(F14/E14-1,"") -> -0.75288889 | G15: =IFERROR(G14/F14-1,"") -> 0.097122302 | H15: =IFERROR(H14/G14-1,"") -> -0.99016393 | I15: =IFERROR(I14/H14-1,"") -> 4.3333333 | J15: =IFERROR(J14/I14-1,"") -> -0.0625 | K15: =IFERROR(K14/J14-1,"") -> -0.13333333 | L15: =L14/K14-1 -> -0.076923077 | M15: 0 | N15: 0 | O15: 0 | P15: 0 | R15: Civil Normalised Growth | S15: =AVERAGE(J6:K6) -> 0.18935903
R16: Defence Normalised Growth | S16: =AVERAGE(J9:K9) -> 0.082217078
A17: Group Underlying Revenue | B17: =Historical_FS!B42 -> 13783 | C17: =Historical_FS!C42 -> 13671 | D17: =Historical_FS!D42 -> 15067 | E17: =Historical_FS!E42 -> 15450 | F17: =Historical_FS!F42 -> 11430 | G17: =Historical_FS!G42 -> 10947 | H17: =Historical_FS!H42 -> 12691 | I17: =Historical_FS!I42 -> 15409 | ... K17: =Historical_FS!K42 -> 20059 | L17: =SUM(L5,L8,L11,L14) -> 23684.547 | M17: =SUM(M5,M8,M11,M14) -> 26325.011 | N17: =SUM(N5,N8,N11,N14) -> 28811.767 | O17: =SUM(O5,O8,O11,O14) -> 31037.626 | P17: =SUM(P5,P8,P11,P14) -> 32905.412 | R17: Power Systems Normalised Growth | S17: =AVERAGE(J12:K12) -> 0.11088005
A18: YoY Growth % | C18: =IFERROR(C17/B17-1,"") -> -0.0081259523 | D18: =IFERROR(D17/C17-1,"") -> 0.10211396 | E18: =IFERROR(E17/D17-1,"") -> 0.025419792 | F18: =IFERROR(F17/E17-1,"") -> -0.26019417 | G18: =IFERROR(G17/F17-1,"") -> -0.042257218 | H18: =IFERROR(H17/G17-1,"") -> 0.15931305 | I18: =IFERROR(I17/H17-1,"") -> 0.21416752 | J18: =IFERROR(J17/I17-1,"") -> 0.15828412 | K18: =IFERROR(K17/J17-1,"") -> 0.12387943 | L18: =L17/K17-1 -> 0.18074415 | M18: =M17/L17-1 -> 0.11148467 | N18: =N17/M17-1 -> 0.094463654 | O18: =O17/N17-1 -> 0.077255194 | P18: =P17/O17-1 -> 0.060178119 | R18: Group Normalised Growth | S18: =AVERAGE(J18:K18) -> 0.14108177
R20: FY2026E BASE CASE
A21: MARGIN DRIVERS | R21: Civil Aerospace Growth | S21: =MIN(S10,S15) -> 0.14845133
A22: Civil Aerospace EBIT Margin | B22: =Historical_FS!B47 -> 0.051931513 | C22: =Historical_FS!C47 -> -0.05198545 | D22: =Historical_FS!D47 -> -0.02195717 | E22: =Historical_FS!E47 -> 0.0054274084 | F22: =Historical_FS!F47 -> -0.50019732 | G22: =Historical_FS!G47 -> -0.037918871 | H22: =Historical_FS!H47 -> 0.02514949 | I22: =Historical_FS!I47 -> 0.11567774 | ... K22: =Historical_FS!K47 -> 0.20516278 | L22: =$S$123/$S$103 -> 0.23633904 | M22: =$S$110 -> 0.22 | N22: =$S$110 -> 0.22 | O22: =$S$110 -> 0.22 | P22: =$S$110 -> 0.22 | R22: Defence Growth | S22: =AVERAGE(S6,S16) -> 0.087339678
A23: Defence EBIT Margin | B23: =Historical_FS!B49 -> 0.17383431 | C23: =Historical_FS!C49 -> 0.1427673 | D23: =Historical_FS!D49 -> 0.13668374 | E23: =Historical_FS!E49 -> 0.12769231 | F23: =Historical_FS!F49 -> 0.13740686 | G23: =Historical_FS!G49 -> 0.13568884 | H23: =Historical_FS!H49 -> 0.11803279 | I23: =Historical_FS!I49 -> 0.13784646 | ... K23: =Historical_FS!K49 -> 0.14438391 | L23: =$S$124/$S$104 -> 0.17842666 | M23: =$S$111 -> 0.15 | N23: =$S$111 -> 0.15 | O23: =$S$111 -> 0.15 | P23: =$S$111 -> 0.15 | R23: Power Systems Growth | S23: =AVERAGE(S7,S17) -> 0.12287171
A24: Power Systems EBIT Margin | B24: =Historical_FS!B51 -> 0.071939736 | C24: =Historical_FS!C51 -> 0.086768617 | D24: =Historical_FS!D51 -> 0.091729761 | E24: =Historical_FS!E51 -> 0.10352609 | F24: =Historical_FS!F51 -> 0.068738574 | G24: =Historical_FS!G51 -> 0.088032012 | H24: =Historical_FS!H51 -> 0.083955781 | I24: =Historical_FS!I51 -> 0.10408266 | ... K24: =Historical_FS!K51 -> 0.1741619 | L24: =$S$125/$S$105 -> 0.1957269 | M24: =$S$112 -> 0.19 | N24: =$S$112 -> 0.19 | O24: =$S$112 -> 0.19 | P24: =$S$112 -> 0.19
A25: Group Underlying EBIT Margin | B25: =Historical_FS!B11 -> 0.066386128 | C25: =Historical_FS!C11 -> 0.022383147 | D25: =Historical_FS!D11 -> 0.040884051 | E25: =Historical_FS!E11 -> 0.052297735 | F25: =Historical_FS!F11 -> -0.17567804 | G25: =Historical_FS!G11 -> 0.03781858 | H25: =Historical_FS!H11 -> 0.05137499 | I25: =Historical_FS!I11 -> 0.10318645 | ... K25: =Historical_FS!K11 -> 0.17259086 | R25: Civil Aerospace 2016-25 CAGR | S25: =(K5/B5)^(1/9)-1 -> 0.043663894
R26: Defence 2016-25 CAGR | S26: =(K8/B8)^(1/9)-1 -> 0.089349381
A27: OPERATING PROFIT BUILD | R27: Power Systems 2016-25 CAGR | S27: =(K11/B11)^(1/9)-1 -> 0.070265004
A28: Civil Aerospace Operating Profit | B28: =Historical_FS!B46 -> 367 | C28: =Historical_FS!C46 -> -343 | D28: =Historical_FS!D46 -> -162 | E28: =Historical_FS!E46 -> 44 | F28: =Historical_FS!F46 -> -2535 | G28: =Historical_FS!G46 -> -172 | H28: =Historical_FS!H46 -> 143 | I28: =Historical_FS!I46 -> 850 | ... K28: =Historical_FS!K46 -> 2130 | L28: =$S$123 -> 2980.8814 | M28: =M5*M22 -> 3114.0333 | N28: =N5*N22 -> 3413.1599 | O28: =O5*O22 -> 3651.6058 | P28: =P5*P22 -> 3811.0491 | R28: Group Revenue 2016-25 CAGR | S28: =(K17/B17)^(1/9)-1 -> 0.042574936
A29: Defence Operating Profit | B29: =Historical_FS!B48 -> 384 | C29: =Historical_FS!C48 -> 454 | D29: =Historical_FS!D48 -> 427 | E29: =Historical_FS!E48 -> 415 | F29: =Historical_FS!F48 -> 461 | G29: =Historical_FS!G48 -> 457 | H29: =Historical_FS!H48 -> 432 | I29: =Historical_FS!I48 -> 562 | ... K29: =Historical_FS!K48 -> 689 | L29: =$S$124 -> 937.74433 | M29: =M8*M23 -> 857.59415 | N29: =N8*N23 -> 933.3579 | O29: =O8*O23 -> 1016.2839 | P29: =P8*P23 -> 1107.0882
A30: Power Systems Operating Profit | B30: =Historical_FS!B50 -> 191 | C30: =Historical_FS!C50 -> 261 | D30: =Historical_FS!D50 -> 315 | E30: =Historical_FS!E50 -> 367 | F30: =Historical_FS!F50 -> 188 | G30: =Historical_FS!G50 -> 242 | H30: =Historical_FS!H50 -> 281 | I30: =Historical_FS!I50 -> 413 | ... K30: =Historical_FS!K50 -> 852 | L30: =$S$125 -> 1136.035 | M30: =M11*M24 -> 1223.7937 | N30: =N11*N24 -> 1341.9735 | O30: =O11*O24 -> 1453.9165 | P30: =P11*P24 -> 1556.0759 | R30: 2028 MID-TERM MARGIN TARGETS
A31: Other / Corporate Operating Profit/(Loss) | B31: =Historical_FS!B52 -> -27 | C31: =Historical_FS!C52 -> -66 | D31: =Historical_FS!D52 -> 36 | E31: =Historical_FS!E52 -> -18 | F31: =Historical_FS!F52 -> -122 | G31: =Historical_FS!G52 -> -113 | H31: =Historical_FS!H52 -> -204 | I31: =Historical_FS!I52 -> -235 | ... K31: =Historical_FS!K52 -> -209 | L31: =$S$126 -> -177 | M31: =$L31 -> -177 | N31: =$L31 -> -177 | O31: =$L31 -> -177 | P31: =$L31 -> -177 | R31: Civil Aerospace | S31: =AVERAGE(21%,23%) -> 0.22
A32: Group Underlying Operating Profit | B32: =Historical_FS!B10 -> 915 | C32: =Historical_FS!C10 -> 306 | D32: =Historical_FS!D10 -> 616 | E32: =Historical_FS!E10 -> 808 | F32: =Historical_FS!F10 -> -2008 | G32: =Historical_FS!G10 -> 414 | H32: =Historical_FS!H10 -> 652 | I32: =Historical_FS!I10 -> 1590 | ... K32: =Historical_FS!K10 -> 3462 | L32: =SUM(L28:L31) -> 4877.6608 | M32: =SUM(M28:M31) -> 5018.4212 | N32: =SUM(N28:N31) -> 5511.4913 | O32: =SUM(O28:O31) -> 5944.8061 | P32: =SUM(P28:P31) -> 6297.2133 | R32: Defence | S32: =AVERAGE(14%,16%) -> 0.15
A33: Group Underlying EBIT Margin | B33: =IFERROR(B32/B17,"") -> 0.066386128 | C33: =IFERROR(C32/C17,"") -> 0.022383147 | D33: =IFERROR(D32/D17,"") -> 0.040884051 | E33: =IFERROR(E32/E17,"") -> 0.052297735 | F33: =IFERROR(F32/F17,"") -> -0.17567804 | G33: =IFERROR(G32/G17,"") -> 0.03781858 | H33: =IFERROR(H32/H17,"") -> 0.05137499 | I33: =IFERROR(I32/I17,"") -> 0.10318645 | ... P33: =IFERROR(P32/P17,"") -> 0.19137318 | R33: Power Systems | S33: =AVERAGE(18%,20%) -> 0.19
R34: Group | S34: =AVERAGE(18%,20%) -> 0.19
A36: CASH FLOW DRIVERS | R36: MODEL CROSS-CHECK
A37: D&A / Non-Cash Add-backs | B37: =Historical_FS!B23 -> 720 | C37: =Historical_FS!C23 -> 652 | D37: =Historical_FS!D23 -> 756 | E37: =Historical_FS!E23 -> 1068 | F37: =Historical_FS!F23 -> 1048 | G37: =Historical_FS!G23 -> 971 | H37: =Historical_FS!H23 -> 953 | I37: =Historical_FS!I23 -> 978 | ... K37: =Historical_FS!K23 -> 900 | L37: =L17*L38 -> 1131.943 | M37: =M17*M38 -> 1258.1373 | N37: =N17*N38 -> 1376.9855 | O37: =O17*O38 -> 1483.3648 | P37: =P17*P38 -> 1572.6309 | R37: FY2026E Model Operating Profit | S37: =L32 -> 4877.6608
A38: D&A as % of Revenue | B38: =IFERROR(B37/B17,"") -> 0.052238265 | C38: =IFERROR(C37/C17,"") -> 0.047692195 | D38: =IFERROR(D37/D17,"") -> 0.050175881 | E38: =IFERROR(E37/E17,"") -> 0.069126214 | F38: =IFERROR(F37/F17,"") -> 0.091688539 | G38: =IFERROR(G37/G17,"") -> 0.0887001 | H38: =IFERROR(H37/H17,"") -> 0.075092585 | I38: =IFERROR(I37/I17,"") -> 0.063469401 | ... K38: =IFERROR(K37/K17,"") -> 0.04486764 | L38: =$S$54 -> 0.04779247 | M38: =$S$54 -> 0.04779247 | N38: =$S$54 -> 0.04779247 | O38: =$S$54 -> 0.04779247 | P38: =$S$54 -> 0.04779247 | R38: FY2026 Guidance Low | S38: =4700 -> 4700
R39: FY2026 Guidance High | S39: =4900 -> 4900
A40: Capital Expenditure | B40: =Historical_FS!B24 -> -1201 | C40: =Historical_FS!C24 -> -1377 | D40: =Historical_FS!D24 -> -1585 | E40: =Historical_FS!E24 -> -1338 | F40: =Historical_FS!F24 -> -895 | G40: =Historical_FS!G24 -> -496 | H40: =Historical_FS!H24 -> -504 | I40: =Historical_FS!I24 -> -695 | ... K40: =Historical_FS!K24 -> -978 | L40: =-L17*L41 -> -1154.7678 | M40: =-M17*M41 -> -1283.5067 | N40: =-N17*N41 -> -1404.7514 | O40: =-O17*O41 -> -1513.2758 | P40: =-P17*P41 -> -1604.3418 | R40: FY2026 Guidance Check | S40: =IF(AND(S37>=S38,S37<=S39),"PASS","CHECK") -> PASS
A41: Capex as % of Revenue | B41: =IFERROR(-B40/B17,"") -> 0.087136327 | C41: =IFERROR(-C40/C17,"") -> 0.10072416 | D41: =IFERROR(-D40/D17,"") -> 0.10519679 | E41: =IFERROR(-E40/E17,"") -> 0.086601942 | F41: =IFERROR(-F40/F17,"") -> 0.078302712 | G41: =IFERROR(-G40/G17,"") -> 0.045309217 | H41: =IFERROR(-H40/H17,"") -> 0.039713183 | I41: =IFERROR(-I40/I17,"") -> 0.045103511 | ... K41: =IFERROR(-K40/K17,"") -> 0.048756169 | L41: =$S$55 -> 0.048756169 | M41: =$S$55 -> 0.048756169 | N41: =$S$55 -> 0.048756169 | O41: =$S$55 -> 0.048756169 | P41: =$S$55 -> 0.048756169
R42: FY2028E Model Operating Profit | S42: =N32 -> 5511.4913
A43: Working Capital Cash Impact | B43: =Historical_FS!B25 -> -55 | C43: =Historical_FS!C25 -> -219 | D43: =Historical_FS!D25 -> 581 | E43: =Historical_FS!E25 -> 531 | F43: =Historical_FS!F25 -> -1527 | G43: =Historical_FS!G25 -> -810 | H43: =Historical_FS!H25 -> -524 | I43: =Historical_FS!I25 -> -356 | ... K43: =Historical_FS!K25 -> 421 | L43: =L17*L44 -> 371.56394 | M43: =M17*M44 -> 412.98762 | N43: =N17*N44 -> 451.99994 | O43: =O17*O44 -> 486.91928 | P43: =P17*P44 -> 516.22117 | R43: FY2028 Target Low | S43: =4900 -> 4900
A44: Working Capital as % of Revenue | B44: =IFERROR(B43/B17,"") -> -0.003990423 | C44: =IFERROR(C43/C17,"") -> -0.016019311 | D44: =IFERROR(D43/D17,"") -> 0.038561094 | E44: =IFERROR(E43/E17,"") -> 0.034368932 | F44: =IFERROR(F43/F17,"") -> -0.1335958 | G44: =IFERROR(G43/G17,"") -> -0.073992875 | H44: =IFERROR(H43/H17,"") -> -0.041289103 | I44: =IFERROR(I43/I17,"") -> -0.023103381 | ... K44: =IFERROR(K43/K17,"") -> 0.020988085 | L44: =$S$56 -> 0.015688032 | M44: =$S$56 -> 0.015688032 | N44: =$S$56 -> 0.015688032 | O44: =$S$56 -> 0.015688032 | P44: =$S$56 -> 0.015688032 | R44: FY2028 Target High | S44: =5200 -> 5200
R45: FY2028 Profit Check | S45: =IF(AND(S42>=S43,S42<=S44),"PASS","CHECK") -> CHECK
A46: Effective Tax Rate | B46: =Historical_FS!B18 -> 0.13028473 | C46: =Historical_FS!C18 -> 0.13211904 | D46: =Historical_FS!D18 -> -0.18798778 | E46: =Historical_FS!E18 -> -0.47138047 | F46: =Historical_FS!F18 -> -0.10789568 | G46: =Historical_FS!G18 -> 1.4217687 | H46: =Historical_FS!H18 -> 0.20505992 | I46: =Historical_FS!I18 -> 0.0094767202 | ... K46: =Historical_FS!K18 -> 0.15847152 | L46: =$S$57 -> 0.25 | M46: =$S$57 -> 0.25 | N46: =$S$57 -> 0.25 | O46: =$S$57 -> 0.25 | P46: =$S$57 -> 0.25 | R46: FY2028E Model EBIT Margin | S46: =N33 -> 0.19129306
R47: FY2028 Margin Target Low | S47: =18% -> 0.18
A48: Operating Tax Expense | L48: =-L32*L46 -> -1219.4152 | M48: =-M32*M46 -> -1254.6053 | N48: =-N32*N46 -> -1377.8728 | O48: =-O32*O46 -> -1486.2015 | P48: =-P32*P46 -> -1574.3033 | R48: FY2028 Margin Target High | S48: =20% -> 0.2
A49: NOPAT | L49: =L32+L48 -> 3658.2456 | M49: =M32+M48 -> 3763.8159 | N49: =N32+N48 -> 4133.6184 | O49: =O32+O48 -> 4458.6046 | P49: =P32+P48 -> 4722.9099 | R49: FY2028 Margin Check | S49: =IF(AND(S46>=S47,S46<=S48),"PASS","CHECK") -> PASS
A51: Unlevered Free Cash Flow | L51: =L49+L37+L40+L43 -> 4006.9847 | M51: =M49+M37+M40+M43 -> 4151.4341 | N51: =N49+N37+N40+N43 -> 4557.8525 | O51: =O49+O37+O40+O43 -> 4915.6129 | P51: =P49+P37+P40+P43 -> 5207.4202 | R51: FY2028 Profit vs Target High | S51: =S42-S44 -> 311.49125
R53: NORMALISED CASH FLOW DRIVERS
R54: D&A % of Revenue | S54: =MEDIAN(I38:K38) -> 0.04779247
R55: Capex % of Revenue | S55: =MEDIAN(I41:K41) -> 0.048756169
R56: Working Capital Cash Impact % of Revenue | S56: =MEDIAN(I44:K44) -> 0.015688032
R57: Normalised Operating Tax Rate | S57: =25% -> 0.25
R58: 3Y Aggregate Effective Tax Rate | S58: =-SUM(Historical_FS!I17:K17)/SUM(Historical_FS!I16:K16) -> 0.075198344
R59: 5Y Aggregate Effective Tax Rate | S59: =-SUM(Historical_FS!G17:K17)/SUM(Historical_FS!G16:K16) -> 0.014897959
R60: Tax Forecast Method | S60: Normalised marginal tax rate
R62: H1 2026 ACTUALS / UPDATED GUIDANCE
R63: H1 2026 Underlying Revenue | S63: =11279 -> 11279
R64: H1 2026 Underlying Operating Profit | S64: =2534 -> 2534
R65: H1 2026 Group EBIT Margin | S65: =S64/S63 -> 0.22466531
R67: FY2026 Guidance Low | S67: =4700 -> 4700
R68: FY2026 Guidance High | S68: =4900 -> 4900
R69: FY2026 Guidance Midpoint | S69: =AVERAGE(S67:S68) -> 4800
R72: H1 2026 DIVISIONAL MARGINS
R73: Civil Aerospace | S73: =25.3% -> 0.253
R74: Defence | S74: =21% -> 0.21
R75: Power Systems | S75: =20.3% -> 0.203
R77: Civil H1 Revenue | S77: =6186 -> 6186
R78: Civil H1 Operating Profit | S78: =1567 -> 1567
R79: Defence H1 Revenue | S79: =2484 -> 2484
R80: Defence H1 Operating Profit | S80: =522 -> 522
R81: Power Systems H1 Revenue | S81: =2604 -> 2604
R82: Power Systems H1 Operating Profit | S82: =528 -> 528
R83: All Other Businesses H1 Revenue | S83: =5 -> 5
R84: All Other Businesses H1 Operating Profit/(Loss) | S84: =-30 -> -30
R85: Corporate / Eliminations H1 Profit/(Loss) | S85: =-53 -> -53
R87: H1 2025 COMPARATIVES
R88: Civil H1 2025 Revenue | S88: =4786 -> 4786
R89: Defence H1 2025 Revenue | S89: =2223 -> 2223
R90: Power Systems H1 2025 Revenue | S90: =2042 -> 2042
R91: All Other H1 2025 Revenue | S91: =6 -> 6
R93: Civil H2 2025 Revenue | S93: =K5-S88 -> 5596
R94: Defence H2 2025 Revenue | S94: =K8-S89 -> 2549
R95: Power Systems H2 2025 Revenue | S95: =K11-S90 -> 2850
R96: Other H2 2025 Revenue | S96: =K14-S91 -> 7
R98: Civil H2 2026 Forecast | S98: =S93*(1+$S$21) -> 6426.7336
R99: Defence H2 2026 Forecast | S99: =S94*(1+$S$22) -> 2771.6288
R100: Power Systems H2 2026 Forecast | S100: =S95*(1+$S$23) -> 3200.1844
R101: Other H2 2026 Forecast | S101: =S96 -> 7
R103: Civil FY2026E Updated | S103: =S77+S98 -> 12612.734
R104: Defence FY2026E Updated | S104: =S79+S99 -> 5255.6288
R105: Power Systems FY2026E Updated | S105: =S81+S100 -> 5804.1844
R106: Other FY2026E Updated | S106: =S83+S101 -> 12
R107: Group FY2026E Updated | S107: =SUM(S103:S106) -> 23684.547
R109: H2 2026 NORMALISED MARGINS
R110: Civil Aerospace H2 Margin | S110: =$S$31 -> 0.22
R111: Defence H2 Margin | S111: =S$32 -> 0.15
R112: Power Systems H2 Margin | S112: =S$33 -> 0.19
R113: H1 2025 Other / Corporate Profit/(Loss) | S113: =-115 -> -115
R114: H2 2025 Other / Corporate Profit/(Loss) | S114: =K31-S113 -> -94
R116: H2 2026 OPERATING PROFIT
...

Sheet Forecast_Model
A1: ROLLS-ROYCE FORECAST MODEL
B2: FY2025A | C2: FY2026E | D2: FY2027E | E2: FY2028E | F2: FY2029E | G2: FY2030E
A4: REVENUE
A5: Civil Aerospace Revenue | B5: =Operating_Drivers!K5 -> 10382 | C5: =Operating_Drivers!L5 -> 12612.734 | D5: =Operating_Drivers!M5 -> 14154.697 | E5: =Operating_Drivers!N5 -> 15514.363 | F5: =Operating_Drivers!O5 -> 16598.208 | G5: =Operating_Drivers!P5 -> 17322.951
A6: Defence Revenue | B6: =Operating_Drivers!K8 -> 4772 | C6: =Operating_Drivers!L8 -> 5255.6288 | D6: =Operating_Drivers!M8 -> 5717.2943 | E6: =Operating_Drivers!N8 -> 6222.386 | F6: =Operating_Drivers!O8 -> 6775.2261 | G6: =Operating_Drivers!P8 -> 7380.5883
A7: Power Systems Revenue | B7: =Operating_Drivers!K11 -> 4892 | C7: =Operating_Drivers!L11 -> 5804.1844 | D7: =Operating_Drivers!M11 -> 6441.0197 | E7: =Operating_Drivers!N11 -> 7063.0183 | F7: =Operating_Drivers!O11 -> 7652.1919 | G7: =Operating_Drivers!P11 -> 8189.8732
A8: Other / Legacy / New Markets Revenue | B8: =Operating_Drivers!K14 -> 13 | C8: =Operating_Drivers!L14 -> 12 | D8: =Operating_Drivers!M14 -> 12 | E8: =Operating_Drivers!N14 -> 12 | F8: =Operating_Drivers!O14 -> 12 | G8: =Operating_Drivers!P14 -> 12
A9: Group Underlying Revenue | B9: =Operating_Drivers!K17 -> 20059 | C9: =Operating_Drivers!L17 -> 23684.547 | D9: =Operating_Drivers!M17 -> 26325.011 | E9: =Operating_Drivers!N17 -> 28811.767 | F9: =Operating_Drivers!O17 -> 31037.626 | G9: =Operating_Drivers!P17 -> 32905.412
A10: YoY Growth % | C10: =C9/B9-1 -> 0.18074415 | D10: =D9/C9-1 -> 0.11148467 | E10: =E9/D9-1 -> 0.094463654 | F10: =F9/E9-1 -> 0.077255194 | G10: =G9/F9-1 -> 0.060178119
A12: OPERATING PROFIT
A13: Civil Aerospace Operating Profit | B13: =Operating_Drivers!K28 -> 2130 | C13: =Operating_Drivers!L28 -> 2980.8814 | D13: =Operating_Drivers!M28 -> 3114.0333 | E13: =Operating_Drivers!N28 -> 3413.1599 | F13: =Operating_Drivers!O28 -> 3651.6058 | G13: =Operating_Drivers!P28 -> 3811.0491
A14: Defence Operating Profit | B14: =Operating_Drivers!K29 -> 689 | C14: =Operating_Drivers!L29 -> 937.74433 | D14: =Operating_Drivers!M29 -> 857.59415 | E14: =Operating_Drivers!N29 -> 933.3579 | F14: =Operating_Drivers!O29 -> 1016.2839 | G14: =Operating_Drivers!P29 -> 1107.0882
A15: Power Systems Operating Profit | B15: =Operating_Drivers!K30 -> 852 | C15: =Operating_Drivers!L30 -> 1136.035 | D15: =Operating_Drivers!M30 -> 1223.7937 | E15: =Operating_Drivers!N30 -> 1341.9735 | F15: =Operating_Drivers!O30 -> 1453.9165 | G15: =Operating_Drivers!P30 -> 1556.0759
A16: Other / Corporate Operating Profit/(Loss) | B16: =Operating_Drivers!K31 -> -209 | C16: =Operating_Drivers!L31 -> -177 | D16: =Operating_Drivers!M31 -> -177 | E16: =Operating_Drivers!N31 -> -177 | F16: =Operating_Drivers!O31 -> -177 | G16: =Operating_Drivers!P31 -> -177
A17: Group Underlying Operating Profit | B17: =Operating_Drivers!K32 -> 3462 | C17: =Operating_Drivers!L32 -> 4877.6608 | D17: =Operating_Drivers!M32 -> 5018.4212 | E17: =Operating_Drivers!N32 -> 5511.4913 | F17: =Operating_Drivers!O32 -> 5944.8061 | G17: =Operating_Drivers!P32 -> 6297.2133
A18: Group EBIT Margin | B18: =Operating_Drivers!K33 -> 0.17259086 | C18: =Operating_Drivers!L33 -> 0.20594275 | D18: =Operating_Drivers!M33 -> 0.1906332 | E18: =Operating_Drivers!N33 -> 0.19129306 | F18: =Operating_Drivers!O33 -> 0.19153547 | G18: =Operating_Drivers!P33 -> 0.19137318
A20: UNLEVERED FREE CASH FLOW
A21: EBIT | B21: =B17 -> 3462 | C21: =C17 -> 4877.6608 | D21: =D17 -> 5018.4212 | E21: =E17 -> 5511.4913 | F21: =F17 -> 5944.8061 | G21: =G17 -> 6297.2133
A22: Operating Tax Rate | C22: =Operating_Drivers!L46 -> 0.25 | D22: =Operating_Drivers!M46 -> 0.25 | E22: =Operating_Drivers!N46 -> 0.25 | F22: =Operating_Drivers!O46 -> 0.25 | G22: =Operating_Drivers!P46 -> 0.25
A23: Operating Tax Expense | C23: =Operating_Drivers!L48 -> -1219.4152 | D23: =Operating_Drivers!M48 -> -1254.6053 | E23: =Operating_Drivers!N48 -> -1377.8728 | F23: =Operating_Drivers!O48 -> -1486.2015 | G23: =Operating_Drivers!P48 -> -1574.3033
A24: NOPAT | C24: =Operating_Drivers!L49 -> 3658.2456 | D24: =Operating_Drivers!M49 -> 3763.8159 | E24: =Operating_Drivers!N49 -> 4133.6184 | F24: =Operating_Drivers!O49 -> 4458.6046 | G24: =Operating_Drivers!P49 -> 4722.9099
A25: D&A / Non-Cash Add-backs | C25: =Operating_Drivers!L37 -> 1131.943 | D25: =Operating_Drivers!M37 -> 1258.1373 | E25: =Operating_Drivers!N37 -> 1376.9855 | F25: =Operating_Drivers!O37 -> 1483.3648 | G25: =Operating_Drivers!P37 -> 1572.6309
A26: Capital Expenditure | C26: =Operating_Drivers!L40 -> -1154.7678 | D26: =Operating_Drivers!M40 -> -1283.5067 | E26: =Operating_Drivers!N40 -> -1404.7514 | F26: =Operating_Drivers!O40 -> -1513.2758 | G26: =Operating_Drivers!P40 -> -1604.3418
A27: Working Capital Cash Impact | C27: =Operating_Drivers!L43 -> 371.56394 | D27: =Operating_Drivers!M43 -> 412.98762 | E27: =Operating_Drivers!N43 -> 451.99994 | F27: =Operating_Drivers!O43 -> 486.91928 | G27: =Operating_Drivers!P43 -> 516.22117
A28: Unlevered Free Cash Flow | C28: =Operating_Drivers!L51 -> 4006.9847 | D28: =Operating_Drivers!M51 -> 4151.4341 | E28: =Operating_Drivers!N51 -> 4557.8525 | F28: =Operating_Drivers!O51 -> 4915.6129 | G28: =Operating_Drivers!P51 -> 5207.4202
A29: UFCF Margin | C29: =IFERROR(C28/C9,"") -> 0.1691814 | D29: =IFERROR(D28/D9,"") -> 0.15769924 | E29: =IFERROR(E28/E9,"") -> 0.15819413 | F29: =IFERROR(F28/F9,"") -> 0.15837593 | G29: =IFERROR(G28/G9,"") -> 0.15825422
A31: MODEL CHECK
A32: Segment Revenue Reconciliation | C32: =C9-SUM(C5:C8) -> 0 | D32: =D9-SUM(D5:D8) -> 0 | E32: =E9-SUM(E5:E8) -> 0 | F32: =F9-SUM(F5:F8) -> 0 | G32: =G9-SUM(G5:G8) -> 0
A33: Segment Operating Profit Reconciliation | C33: =C17-SUM(C13:C16) -> 0 | D33: =D17-SUM(D13:D16) -> 0 | E33: =E17-SUM(E13:E16) -> 0 | F33: =F17-SUM(F13:F16) -> 0 | G33: =G17-SUM(G13:G16) -> 0

Sheet DCF
A1: ROLLS-ROYCE DCF VALUATION
A3: VALUATION PARAMETERS
A4: Valuation Reference Date | B4: 46203
A5: Currency / Units | B5: GBP £m
A7: WACC
A8: Risk-Free Rate | B8: =4.83% -> 0.0483
A9: Beta | B9: =1.2 -> 1.2
A10: Equity Risk Premium | B10: =4.17% -> 0.0417
A11: Cost of Equity | B11: =B8+B9*B10 -> 0.09834
A13: H1 2026 Underlying Interest Payable | B13: =103 -> 103
A14: Debt + Lease Liabilities - Dec 2025 | B14: =4272 -> 4272
A15: Debt + Lease Liabilities - Jun 2026 | B15: =4311 -> 4311
A16: Pre-Tax Cost of Debt | B16: =(B13*2)/AVERAGE(B14:B15) -> 0.048001864
A17: Normalised Tax Rate | B17: =Operating_Drivers!L46 -> 0.25
A18: After-Tax Cost of Debt | B18: =B16*(1-B17) -> 0.036001398
A20: Share Price - 30 Jun 2026 (£) | B20: =14.45 -> 14.45
A21: Diluted Shares Outstanding (m) | B21: =8368 -> 8368
A22: Market Value of Equity | B22: =B20*B21 -> 120917.6
A23: Debt + Lease Liabilities | B23: =B15 -> 4311
A24: Equity Weight | B24: =B22/(B22+B23) -> 0.96557496
A25: Debt Weight | B25: =B23/(B22+B23) -> 0.034425043
A26: WACC | B26: =B24*B11+B25*B18 -> 0.096193991
A27: Terminal Growth Rate | B27: =2.5% -> 0.025
A30: H1 2026 UFCF SUPPORT
A31: H1 Underlying EBIT | B31: =2534 -> 2534
A32: Normalised Operating Tax Rate | B32: =B17 -> 0.25
A33: Operating Tax Expense | B33: =-B31*B32 -> -633.5
A34: NOPAT | B34: =B31+B33 -> 1900.5
A35: D&A / Non-Cash Add-backs | B35: =426 -> 426
A36: Capital Expenditure | B36: =-362 -> -362
A37: Working Capital Cash Impact | B37: =65 -> 65
A38: H1 2026 UFCF | B38: =SUM(B34:B37) -> 2029.5
A41: DCF VALUATION
B42: FY2026 Stub | C42: FY2027E | D42: FY2028E | E42: FY2029E | F42: FY2030E
A43: Full-Year UFCF | B43: =Forecast_Model!C28 -> 4006.9847 | C43: =Forecast_Model!D28 -> 4151.4341 | D43: =Forecast_Model!E28 -> 4557.8525 | E43: =Forecast_Model!F28 -> 4915.6129 | F43: =Forecast_Model!G28 -> 5207.4202
A44: Less: H1 2026 UFCF | B44: =-$B$38 -> -2029.5
A45: DCF Cash Flow | B45: =SUM(B43:B44) -> 1977.4847 | C45: =C43 -> 4151.4341 | D45: =D43 -> 4557.8525 | E45: =E43 -> 4915.6129 | F45: =F43 -> 5207.4202
A46: Discount Period | B46: 0.25 | C46: 1 | D46: 2 | E46: 3 | F46: 4
A47: Discount Factor | B47: =1/(1+$B$26)^B46 -> 0.97730056 | C47: =1/(1+$B$26)^C46 -> 0.91224729 | D47: =1/(1+$B$26)^D46 -> 0.83219512 | E47: =1/(1+$B$26)^E46 -> 0.75916775 | F47: =1/(1+$B$26)^F46 -> 0.69254872
A48: PV of UFCF | B48: =B45*B47 -> 1932.5969 | C48: =C45*C47 -> 3787.1345 | D48: =D45*D47 -> 3793.0226 | E48: =E45*E47 -> 3731.7748 | F48: =F45*F47 -> 3606.3922
A51: TERMINAL VALUE
A52: FY2030 UFCF | B52: =F45 -> 5207.4202
A53: Terminal Growth | B53: =$B$27 -> 0.025
A54: WACC | B54: =$B$26 -> 0.096193991
A55: Terminal Value | B55: =B52*(1+B53)/(B54-B53) -> 74972.699
A56: Terminal Discount Period | B56: =4.5 -> 4.5
A57: PV of Terminal Value | B57: =B55/(1+$B$26)^B56 -> 49591.789
A60: Enterprise Value | B60: =SUM(B48:F48)+B57 -> 66442.71
A61: Net Cash | B61: =2136 -> 2136
A62: Equity Value | B62: =SUM(B60:B61) -> 68578.71
A63: Diluted Shares (m) | B63: =$B$21 -> 8368
A64: Implied Value per Share (£) | B64: =B62/B63 -> 8.1953525
A65: Reference Share Price (£) | B65: =$B$20 -> 14.45
A66: Upside / (Downside) | B66: =B64/B65-1 -> -0.43284758
A68: MARKET VALUATION CROSS-CHECK
A69: Reference Market Capitalisation | B69: =B20*B21 -> 120917.6
A70: Reference Market Enterprise Value | B70: =B69-B61 -> 118781.6
A71: DCF Enterprise Value Discount to Market | B71: =B60/B70-1 -> -0.4406313
A73: Terminal Value % of Enterprise Value | B73: =B57/B60 -> 0.7463842
A75: FY2030E UFCF | B75: =F45 -> 5207.4202
A76: Market EV / FY2030E UFCF | B76: =B70/B75 -> 22.810066

Sheet Comparable_Companies
A1: ROLLS-ROYCE | B1: COMPARABLE | C1: COMPANIES
A3: TRADING | B3: COMPARABLES | N3: MARKET DATA SUPPORT
A5: Company | B5: Ticker | C5: Primary Exposure | D5: Market Cap | E5: Enterprise Value | F5: FY2025 Revenue / Sales (Local £/€/$m) | G5: FY2025 EBIT / Operating Profit (Local £/€/$m) | H5: FY2025 EBITDA (Local £/€/$m) | I5: EV/Revenue | J5: EV/EBIT | K5: EV/EBITDA | L5: Metric Basis | N5: Company | O5: Share Price - 30 Jun 2026 | P5: Shares Outstanding (m) | Q5: Net Debt / (Cash) | R5: Market Cap | S5: Enterprise Value
A6: GE Aerospace | B6: GE | D6: =R6 -> 387768.24 | E6: =S6 -> 396580.24 | F6: 42322 | G6: 9055 | I6: =E6/F6 -> 9.3705458 | J6: =E6/G6 -> 43.796824 | L6: Adjusted | N6: GE Aerospace | O6: {=_xlfn.STOCKHISTORY(B6,DATE(2026,6,30),DATE(2026,6,30),0,0,1)} -> 373.73 | P6: 1037.5625 | Q6: 8812 | R6: =O6*P6 -> 387768.24 | S6: =R6+Q6 -> 396580.24
A7: Safran | B7: SAF | D7: =R7 -> 143017.62 | E7: =S7 -> 141350.62 | F7: 31329 | G7: 5197 | I7: =E7/F7 -> 4.5118141 | J7: =E7/G7 -> 27.198504 | L7: Adjusted | N7: Safran | O7: {=_xlfn.STOCKHISTORY("XPAR:SAF",DATE(2026,6,30),DATE(2026,6,30),0,0,1)} -> 345 | P7: 414.54384 | Q7: -1667 | R7: =O7*P7 -> 143017.62 | S7: =R7+Q7 -> 141350.62
A8: RTX | B8: RTX | D8: =R8 -> 255710.15 | E8: =S8 -> 284559.15 | F8: 88603 | G8: 11389 | I8: =E8/F8 -> 3.2116198 | J8: =E8/G8 -> 24.985438 | L8: Adjusted | N8: RTX | O8: {=_xlfn.STOCKHISTORY("XNYS:RTX",DATE(2026,6,30),DATE(2026,6,30),0,0,1)} -> 189.73 | P8: 1347.7581 | Q8: 28849 | R8: =O8*P8 -> 255710.15 | S8: =R8+Q8 -> 284559.15
A9: MTU Aero Engines | B9: MTX | D9: =R9 -> 19603.516 | E9: =S9 -> 20827.516 | F9: 8717 | G9: 1351 | I9: =E9/F9 -> 2.3892987 | J9: =E9/G9 -> 15.41637 | L9: Adjusted | N9: MTU Aero Engines | O9: {=_xlfn.STOCKHISTORY("XETR:MTX",DATE(2026,6,30),DATE(2026,6,30),0,0,1)} -> 363.9 | P9: 53.870614 | Q9: 1224 | R9: =O9*P9 -> 19603.516 | S9: =R9+Q9 -> 20827.516
A10: BAE Systems | B10: BA. | D10: =R10 -> 55227.8 | E10: =S10 -> 58400.8 | F10: 30662 | G10: 3322 | I10: =E10/F10 -> 1.9046638 | J10: =E10/G10 -> 17.580012 | L10: Sales / Underlying EBIT | N10: BAE Systems | O10: {=_xlfn.STOCKHISTORY("XLON:BA.",DATE(2026,6,30),DATE(2026,6,30),0,0,1)} -> 1844 | P10: 2995 | Q10: 3173 | R10: =(O10/100)*P10 -> 55227.8 | S10: =R10+Q10 -> 58400.8
A11: Rolls-Royce | B11: RR. | D11: =R11 -> 120684.42 | E11: =S11 -> 118548.42 | F11: 20059 | G11: 3462 | I11: =E11/F11 -> 5.9099867 | J11: =E11/G11 -> 34.242757 | L11: Underlying | N11: Rolls-Royce | O11: {=_xlfn.STOCKHISTORY("XLON:RR.",DATE(2026,6,30),DATE(2026,6,30),0,0,1)} -> 1444.6 | P11: 8354.1758 | Q11: -2136 | R11: =(O11/100)*P11 -> 120684.42 | S11: =R11+Q11 -> 118548.42
A14: PEER VALUATION SUMMARY
A15: Statistic | B15: EV / Revenue | C15: EV / EBIT
A16: Minimum | B16: =MIN(I6:I10) -> 1.9046638 | C16: =MIN(J6:J10) -> 15.41637
A17: 25th Percentile | B17: =_xlfn.QUARTILE.INC(I6:I10,1) -> 2.3892987 | C17: =_xlfn.QUARTILE.INC(J6:J10,1) -> 17.580012
A18: Median | B18: =MEDIAN(I6:I10) -> 3.2116198 | C18: =MEDIAN(J6:J10) -> 24.985438
A19: 75th Percentile | B19: =_xlfn.QUARTILE.INC(I6:I10,3) -> 4.5118141 | C19: =_xlfn.QUARTILE.INC(J6:J10,3) -> 27.198504
A20: Maximum | B20: =MAX(I6:I10) -> 9.3705458 | C20: =MAX(J6:J10) -> 43.796824
A22: ROLLS-ROYCE CURRENT TRADING
A23: EV / Revenue | B23: =I11 -> 5.9099867
A24: EV / EBIT | B24: =J11 -> 34.242757
A27: IMPLIED VALUATION
A28: Metric | B28: EV/Revenue | C28: EV/EBIT
A29: Peer Median Multiple | B29: =B18 -> 3.2116198 | C29: =C18 -> 24.985438
A30: Rolls-Royce FY2025 Metric | B30: =F11 -> 20059 | C30: =G11 -> 3462
A31: Implied Enterprise Value | B31: =B29*B30 -> 64421.882 | C31: =C29*C30 -> 86499.586
A32: Net Cash | B32: =DCF!$B$61 -> 2136 | C32: =DCF!$B$61 -> 2136
A33: Implied Equity Value | B33: =SUM(B31:B32) -> 66557.882 | C33: =SUM(C31:C32) -> 88635.586
A34: Diluted Shares (m) | B34: =DCF!$B$63 -> 8368 | C34: =DCF!$B$63 -> 8368
A35: Implied Value / Share (£) | B35: =B33/B34 -> 7.9538578 | C35: =C33/C34 -> 10.592207
A36: Reference Share Price (£) | B36: =DCF!$B$65 -> 14.45 | C36: =DCF!$B$65 -> 14.45
A37: Upside / (Downside) | B37: =B35/B36-1 -> -0.44956001 | C37: =C35/C36-1 -> -0.26697531
A39: Comps Midpoint Value / Share | B39: =AVERAGE(B35:C35) -> 9.2730323
A40: Comps Midpoint Upside / (Downside) | B40: =B39/DCF!$B$65-1 -> -0.35826766

Sheet Sensitivity
A1: ROLLS-ROYCE DCF SENSITIVITY
A3: WACC × TERMINAL GROWTH SENSITIVITY | J3: Sensitivity WACC Input | K3: =DCF!$B$26 -> 0.096193991
A4: Implied Value per Share (£) | J4: Sensitivity Terminal Growth Input | K4: =DCF!$B$27 -> 0.025
B5: {=(SUMPRODUCT(DCF!$B$45:$F$45,1/(1+$K$3)^DCF!$B$46:$F$46)+(DCF!$F$45*(1+$K$4)/($K$3-$K$4))/(1+$K$3)^DCF!$B$56+DCF!$B$61)/DCF!$B$63} -> 8.1953525 | C5: 0.08 | D5: 0.085 | E5: 0.09 | F5: 0.095 | G5: 0.1 | H5: 0.105 | I5: 0.11
B6: 0.015 | C6: 9.2101389 | D6: 8.566457 | E6: 8.0091912 | F6: 7.5221176 | G6: 7.09283 | H6: 6.7116803 | I6: 6.3710518
B7: 0.02 | C7: 9.8195681 | D7: 9.0804479 | E7: 8.4475391 | F7: 7.899577 | G7: 7.420614 | H7: 6.9984555 | I7: 6.6236176
B8: 0.025 | C8: 10.539802 | D8: 9.680104 | E8: 8.9533251 | F8: 8.3309592 | G8: 7.7921024 | H8: 7.3210775 | I8: 6.9058969
B9: 0.03 | C9: 11.404084 | D9: 10.388789 | E9: 9.5434088 | F9: 8.8287079 | G9: 8.2166606 | H9: 7.6867159 | I9: 7.2234612
B10: 0.035 | C10: 12.460428 | D10: 11.23921 | E10: 10.24078 | F10: 9.4094148 | G10: 8.7065355 | H10: 8.1045883 | I10: 7.5833673
L12: MARKET-IMPLIED WACC
A13: OPERATING SCENARIO ANALYSIS | L13: Target Share Price | M13: =DCF!$B$65 -> 14.45
L14: Terminal Growth | M14: =DCF!$B$27 -> 0.025
A15: Assumption | B15: Bear | C15: Base | D15: Bull | L15: WACC Input | M15: 0.064903226
A16: Revenue Growth Adjustment | B16: -0.02 | C16: 0 | D16: 0.02 | L16: Implied Share Price | M16: {=(SUMPRODUCT(DCF!$B$45:$F$45,1/(1+$M$15)^DCF!$B$46:$F$46)+(DCF!$F$45*(1+$M$14)/($M$15-$M$14))/(1+$M$15)^DCF!$B$56+DCF!$B$61)/DCF!$B$63} -> 14.449805
A17: EBIT Margin Adjustment | B17: -0.01 | C17: 0 | D17: 0.01 | L17: Market-Implied WACC | M17: =M15 -> 0.064903226
A18: WACC Adjustment | B18: 0.005 | C18: 0 | D18: -0.005
A19: Terminal Growth Rate | B19: 0.02 | C19: 0.025 | D19: 0.03
L20: MARKET-IMPLIED TERMINAL GROWTH
A21: Selected Scenario | B21: Base | L21: Target Share Price | M21: =DCF!$B$65 -> 14.45
L22: WACC | M22: =DCF!$B$26 -> 0.096193991
A23: Selected Revenue Growth Adjustment | B23: =CHOOSE(MATCH($B$21,{"Bear","Base","Bull"},0),$B$16,$C$16,$D$16) -> 0 | L23: Terminal Growth Input | M23: 0.060363962
A24: Selected EBIT Margin Adjustment | B24: =CHOOSE(MATCH($B$21,{"Bear","Base","Bull"},0),$B$17,$C$17,$D$17) -> 0 | L24: Implied Share Price | M24: {=(SUMPRODUCT(DCF!$B$45:$F$45,1/(1+$M$22)^DCF!$B$46:$F$46)+(DCF!$F$45*(1+$M$23)/($M$22-$M$23))/(1+$M$22)^DCF!$B$56+DCF!$B$61)/DCF!$B$63} -> 14.450901
A25: Selected WACC Adjustment | B25: =CHOOSE(MATCH($B$21,{"Bear","Base","Bull"},0),$B$18,$C$18,$D$18) -> 0 | L25: Market-Implied Terminal Growth | M25: =M23 -> 0.060363962
A26: Selected Terminal Growth | B26: =CHOOSE(MATCH($B$21,{"Bear","Base","Bull"},0),$B$19,$C$19,$D$19) -> 0.025
A29: SCENARIO FORECAST | L29: MARKET-IMPLIED REVENUE GROWTH
B30: FY2026E | C30: FY2027E | D30: FY2028E | E30: FY2029E | F30: FY2030E | L30: Target Share Price | M30: =DCF!$B$65 -> 14.45
A31: Base Revenue | B31: =Forecast_Model!C9 -> 23684.547 | C31: =Forecast_Model!D9 -> 26325.011 | D31: =Forecast_Model!E9 -> 28811.767 | E31: =Forecast_Model!F9 -> 31037.626 | F31: =Forecast_Model!G9 -> 32905.412 | L31: Revenue Growth Adjustment Input | M31: 0.18929165
A32: Scenario Revenue | B32: =B31 -> 23684.547 | C32: =B32*(1+(Forecast_Model!D10+$B$23)) -> 26325.011 | D32: =C32*(1+(Forecast_Model!E10+$B$23)) -> 28811.767 | E32: =D32*(1+(Forecast_Model!F10+$B$23)) -> 31037.626 | F32: =E32*(1+(Forecast_Model!G10+$B$23)) -> 32905.412
M33: FY2026E | N33: FY2027E | O33: FY2028E | P33: FY2029E | Q33: FY2030E
A34: Base EBIT Margin | B34: =Forecast_Model!C18 -> 0.20594275 | C34: =Forecast_Model!D18 -> 0.1906332 | D34: =Forecast_Model!E18 -> 0.19129306 | E34: =Forecast_Model!F18 -> 0.19153547 | F34: =Forecast_Model!G18 -> 0.19137318 | L34: Revenue | M34: =Forecast_Model!C9 -> 23684.547 | N34: =M34*(1+Forecast_Model!D10+$M$31) -> 30808.298 | O34: =N34*(1+Forecast_Model!E10+$M$31) -> 39550.316 | P34: =O34*(1+Forecast_Model!F10+$M$31) -> 50092.328 | Q34: =P34*(1+Forecast_Model!G10+$M$31) -> 62588.849
A35: Scenario EBIT Margin | B35: =B34 -> 0.20594275 | C35: =C34+$B$24 -> 0.1906332 | D35: =D34+$B$24 -> 0.19129306 | E35: =E34+$B$24 -> 0.19153547 | F35: =F34+$B$24 -> 0.19137318 | L35: EBIT Margin | M35: =Forecast_Model!C18 -> 0.20594275 | N35: =Forecast_Model!D18 -> 0.1906332 | O35: =Forecast_Model!E18 -> 0.19129306 | P35: =Forecast_Model!F18 -> 0.19153547 | Q35: =Forecast_Model!G18 -> 0.19137318
L36: EBIT | M36: =Forecast_Model!C17 -> 4877.6608 | N36: =N34*N35 -> 5873.0845 | O36: =O34*O35 -> 7565.7011 | P36: =P34*P35 -> 9594.4573 | Q36: =Q34*Q35 -> 11977.827
A37: Scenario EBIT | B37: =B32*B35 -> 4877.6608 | C37: =C32*C35 -> 5018.4212 | D37: =D32*D35 -> 5511.4913 | E37: =E32*E35 -> 5944.8061 | F37: =F32*F35 -> 6297.2133 | L37: UFCF | M37: =Forecast_Model!C28 -> 4006.9847 | N37: =N34*(N35*(1-Operating_Drivers!$S$57)+Operating_Drivers!$S$54-Operating_Drivers!$S$55+Operating_Drivers!$S$56) -> 4858.445 | O37: =O34*(O35*(1-Operating_Drivers!$S$57)+Operating_Drivers!$S$54-Operating_Drivers!$S$55+Operating_Drivers!$S$56) -> 6256.6278 | P37: =P34*(P35*(1-Operating_Drivers!$S$57)+Operating_Drivers!$S$54-Operating_Drivers!$S$55+Operating_Drivers!$S$56) -> 7933.4191 | Q37: =Q34*(Q35*(1-Operating_Drivers!$S$57)+Operating_Drivers!$S$54-Operating_Drivers!$S$55+Operating_Drivers!$S$56) -> 9904.9493
A39: Scenario NOPAT | B39: =B37*(1-Operating_Drivers!$S$57) -> 3658.2456 | C39: =C37*(1-Operating_Drivers!$S$57) -> 3763.8159 | D39: =D37*(1-Operating_Drivers!$S$57) -> 4133.6184 | E39: =E37*(1-Operating_Drivers!$S$57) -> 4458.6046 | F39: =F37*(1-Operating_Drivers!$S$57) -> 4722.9099 | L39: Implied Value / Share | M39: =((M37-DCF!$B$38)/(1+DCF!$B$26)^0.25+N37/(1+DCF!$B$26)^1+O37/(1+DCF!$B$26)^2+P37/(1+DCF!$B$26)^3+Q37/(1+DCF!$B$26)^4+(Q37*(1+DCF!$B$27)/(DCF!$B$26-DCF!$B$27))/(1+DCF!$B$26)^4.5+DCF!$B$61)/DCF!$B$63 -> 14.450003
A40: D&A / Non-Cash Add-backs | B40: =B32*Operating_Drivers!$S$54 -> 1131.943 | C40: =C32*Operating_Drivers!$S$54 -> 1258.1373 | D40: =D32*Operating_Drivers!$S$54 -> 1376.9855 | E40: =E32*Operating_Drivers!$S$54 -> 1483.3648 | F40: =F32*Operating_Drivers!$S$54 -> 1572.6309 | L40: Market-Implied Growth Adjustment | M40: =M31 -> 0.18929165
A41: Capital Expenditure | B41: =-B32*Operating_Drivers!$S$55 -> -1154.7678 | C41: =-C32*Operating_Drivers!$S$55 -> -1283.5067 | D41: =-D32*Operating_Drivers!$S$55 -> -1404.7514 | E41: =-E32*Operating_Drivers!$S$55 -> -1513.2758 | F41: =-F32*Operating_Drivers!$S$55 -> -1604.3418 | L41: Implied Avg FY2027-30 Revenue Growth | M41: =AVERAGE(Forecast_Model!D10:G10)+M31 -> 0.27513706
A42: Working Capital Cash Impact | B42: =B32*Operating_Drivers!$S$56 -> 371.56394 | C42: =C32*Operating_Drivers!$S$56 -> 412.98762 | D42: =D32*Operating_Drivers!$S$56 -> 451.99994 | E42: =E32*Operating_Drivers!$S$56 -> 486.91928 | F42: =F32*Operating_Drivers!$S$56 -> 516.22117
A43: Scenario UFCF | B43: =SUM(B39:B42) -> 4006.9847 | C43: =SUM(C39:C42) -> 4151.4341 | D43: =SUM(D39:D42) -> 4557.8525 | E43: =SUM(E39:E42) -> 4915.6129 | F43: =SUM(F39:F42) -> 5207.4202
L44: MARKET-IMPLIED EBIT MARGIN
A45: Scenario WACC | B45: =DCF!$B$26+$B$25 -> 0.096193991 | L45: Target Share Price | M45: =DCF!$B$65 -> 14.45
A46: Scenario Terminal Growth | B46: =$B$26 -> 0.025 | L46: EBIT Margin Adjustment Input | M46: 0.17116329
M48: FY2026E | N48: FY2027E | O48: FY2028E | P48: FY2029E | Q48: FY2030E
A49: BEAR / BASE / BULL VALUATION | L49: Revenue | M49: =Forecast_Model!C9 -> 23684.547 | N49: =Forecast_Model!D9 -> 26325.011 | O49: =Forecast_Model!E9 -> 28811.767 | P49: =Forecast_Model!F9 -> 31037.626 | Q49: =Forecast_Model!G9 -> 32905.412
A50: Metric | B50: Bear | C50: Base | D50: Bull | L50: EBIT Margin | M50: =Forecast_Model!C18 -> 0.20594275 | N50: =Forecast_Model!D18+$M$46 -> 0.3617965 | O50: =Forecast_Model!E18+$M$46 -> 0.36245635 | P50: =Forecast_Model!F18+$M$46 -> 0.36269876 | Q50: =Forecast_Model!G18+$M$46 -> 0.36253647
A51: Revenue Growth Adjustment | B51: =B16 -> -0.02 | C51: =C16 -> 0 | D51: =D16 -> 0.02 | L51: EBIT | M51: =N49*N50 -> 9524.2966 | N51: =N49*N50 -> 9524.2966 | O51: =O49*O50 -> 10443.008 | P51: =P49*P50 -> 11257.308 | Q51: =Q49*Q50 -> 11929.412
A52: EBIT Margin Adjustment | B52: =B17 -> -0.01 | C52: =C17 -> 0 | D52: =D17 -> 0.01 | L52: UFCF | M52: =Forecast_Model!C28 -> 4006.9847 | N52: =N49*(N50*(1-Operating_Drivers!$S$57)+Operating_Drivers!$S$54-Operating_Drivers!$S$55+Operating_Drivers!$S$56) -> 7530.8407 | O52: =O49*(O50*(1-Operating_Drivers!$S$57)+Operating_Drivers!$S$54-Operating_Drivers!$S$55+Operating_Drivers!$S$56) -> 8256.4902 | P52: =P49*(P50*(1-Operating_Drivers!$S$57)+Operating_Drivers!$S$54-Operating_Drivers!$S$55+Operating_Drivers!$S$56) -> 8899.9896 | Q52: =Q49*(Q50*(1-Operating_Drivers!$S$57)+Operating_Drivers!$S$54-Operating_Drivers!$S$55+Operating_Drivers!$S$56) -> 9431.5691
A53: WACC | B53: =DCF!$B$26+B$18 -> 0.10119399 | C53: =DCF!$B$26+C$18 -> 0.096193991 | D53: =DCF!$B$26+D$18 -> 0.091193991
A54: Terminal Growth | B54: =B19 -> 0.02 | C54: =C19 -> 0.025 | D54: =D19 -> 0.03 | L54: Implied Value / Share | M54: =((M52-DCF!$B$38)/(1+DCF!$B$26)^0.25+N52/(1+DCF!$B$26)^1+O52/(1+DCF!$B$26)^2+P52/(1+DCF!$B$26)^3+Q52/(1+DCF!$B$26)^4+(Q52*(1+DCF!$B$27)/(DCF!$B$26-DCF!$B$27))/(1+DCF!$B$26)^4.5+DCF!$B$61)/DCF!$B$63 -> 14.45
L55: Market-Implied Margin Adjustment | M55: =M46 -> 0.17116329
A56: FY2026E Revenue | B56: =Forecast_Model!$C$9 -> 23684.547 | C56: =Forecast_Model!$C$9 -> 23684.547 | D56: =Forecast_Model!$C$9 -> 23684.547 | L56: Implied FY2030 EBIT Margin | M56: =Forecast_Model!G18+M46 -> 0.36253647
A57: FY2027E Revenue | B57: =B56*(1+Forecast_Model!$D$10+B$51) -> 25851.32 | C57: =C56*(1+Forecast_Model!$D$10+C$51) -> 26325.011 | D57: =D56*(1+Forecast_Model!$D$10+D$51) -> 26798.702
A58: FY2028E Revenue | B58: =B57*(1+Forecast_Model!$E$10+B$51) -> 27776.303 | C58: =C57*(1+Forecast_Model!$E$10+C$51) -> 28811.767 | D58: =D57*(1+Forecast_Model!$E$10+D$51) -> 29866.179
A59: FY2029E Revenue | B59: =B58*(1+Forecast_Model!$F$10+B$51) -> 29366.641 | C59: =C58*(1+Forecast_Model!$F$10+C$51) -> 31037.626 | D59: =D58*(1+Forecast_Model!$F$10+D$51) -> 32770.82
A60: FY2030E Revenue | B60: =B59*(1+Forecast_Model!$G$10+B$51) -> 30546.538 | C60: =C59*(1+Forecast_Model!$G$10+C$51) -> 32905.412 | D60: =D59*(1+Forecast_Model!$G$10+D$51) -> 35398.323
A62: FY2026E UFCF | B62: =Forecast_Model!$C$28 -> 4006.9847 | C62: =Forecast_Model!$C$28 -> 4006.9847 | D62: =Forecast_Model!$C$28 -> 4006.9847
A63: FY2027E UFCF | B63: =B57*((Forecast_Model!$D$18+B$52)*(1-Operating_Drivers!$S$57)+Operating_Drivers!$S$54-Operating_Drivers!$S$55+Operating_Drivers!$S$56) -> 3882.8485 | C63: =C57*((Forecast_Model!$D$18+C$52)*(1-Operating_Drivers!$S$57)+Operating_Drivers!$S$54-Operating_Drivers!$S$55+Operating_Drivers!$S$56) -> 4151.4341 | D63: =D57*((Forecast_Model!$D$18+D$52)*(1-Operating_Drivers!$S$57)+Operating_Drivers!$S$54-Operating_Drivers!$S$55+Operating_Drivers!$S$56) -> 4427.125
A64: FY2028E UFCF | B64: =B58*((Forecast_Model!$E$18+B$52)*(1-Operating_Drivers!$S$57)+Operating_Drivers!$S$54-Operating_Drivers!$S$55+Operating_Drivers!$S$56) -> 4185.7259 | C64: =C58*((Forecast_Model!$E$18+C$52)*(1-Operating_Drivers!$S$57)+Operating_Drivers!$S$54-Operating_Drivers!$S$55+Operating_Drivers!$S$56) -> 4557.8525 | D64: =D58*((Forecast_Model!$E$18+D$52)*(1-Operating_Drivers!$S$57)+Operating_Drivers!$S$54-Operating_Drivers!$S$55+Operating_Drivers!$S$56) -> 4948.6505
A65: FY2029E UFCF | B65: =B59*((Forecast_Model!$F$18+B$52)*(1-Operating_Drivers!$S$57)+Operating_Drivers!$S$54-Operating_Drivers!$S$55+Operating_Drivers!$S$56) -> 4430.7193 | C65: =C59*((Forecast_Model!$F$18+C$52)*(1-Operating_Drivers!$S$57)+Operating_Drivers!$S$54-Operating_Drivers!$S$55+Operating_Drivers!$S$56) -> 4915.6129 | D65: =D59*((Forecast_Model!$F$18+D$52)*(1-Operating_Drivers!$S$57)+Operating_Drivers!$S$54-Operating_Drivers!$S$55+Operating_Drivers!$S$56) -> 5435.8903
A66: FY2030E UFCF | B66: =B60*((Forecast_Model!$G$18+B$52)*(1-Operating_Drivers!$S$57)+Operating_Drivers!$S$54-Operating_Drivers!$S$55+Operating_Drivers!$S$56) -> 4605.0193 | C66: =C60*((Forecast_Model!$G$18+C$52)*(1-Operating_Drivers!$S$57)+Operating_Drivers!$S$54-Operating_Drivers!$S$55+Operating_Drivers!$S$56) -> 5207.4202 | D66: =D60*((Forecast_Model!$G$18+D$52)*(1-Operating_Drivers!$S$57)+Operating_Drivers!$S$54-Operating_Drivers!$S$55+Operating_Drivers!$S$56) -> 5867.4212
A68: PV - FY2026E Stub | B68: =(B62-DCF!$B$38)/(1+B$53)^0.25 -> 1930.3994 | C68: =(C62-DCF!$B$38)/(1+C$53)^0.25 -> 1932.5969 | D68: =(D62-DCF!$B$38)/(1+D$53)^0.25 -> 1934.807
A69: PV - FY2027E UFCF | B69: =B63/(1+B$53)^1 -> 3526.0349 | C69: =C63/(1+C$53)^1 -> 3787.1345 | D69: =D63/(1+D$53)^1 -> 4057.1384
A70: PV - FY2028E UFCF | B70: =B64/(1+B$53)^2 -> 3451.7801 | C70: =C64/(1+C$53)^2 -> 3793.0226 | D70: =D64/(1+D$53)^2 -> 4156.07
A71: PV - FY2029E UFCF | B71: =B65/(1+B$53)^3 -> 3318.0486 | C71: =C65/(1+C$53)^3 -> 3731.7748 | D71: =D65/(1+D$53)^3 -> 4183.741
A72: PV - FY2030E UFCF | B72: =B66/(1+B$53)^4 -> 3131.671 | C72: =C66/(1+C$53)^4 -> 3606.3922 | D72: =D66/(1+D$53)^4 -> 4138.4661
A73: PV of Terminal Value | B73: =(B66*(1+B$54)/(B$53-B$54))/(1+B$53)^4.5 -> 37490.436 | C73: =(C66*(1+C$54)/(C$53-C$54))/(1+C$53)^4.5 -> 49591.789 | D73: =(D66*(1+D$54)/(D$53-D$54))/(1+D$53)^4.5 -> 66683.267
A75: Enterprise Value | B75: =SUM(B68:B73) -> 52848.37 | C75: =SUM(C68:C73) -> 66442.71 | D75: =SUM(D68:D73) -> 85153.489
A76: Net Cash | B76: =DCF!$B$61 -> 2136 | C76: =DCF!$B$61 -> 2136 | D76: =DCF!$B$61 -> 2136
A77: Equity Value | B77: =SUM(B75:B76) -> 54984.37 | C77: =SUM(C75:C76) -> 68578.71 | D77: =SUM(D75:D76) -> 87289.489
A78: Diluted Shares (m) | B78: =DCF!$B$63 -> 8368 | C78: =DCF!$B$63 -> 8368 | D78: =DCF!$B$63 -> 8368
A79: Implied Value / Share (£) | B79: =B77/B78 -> 6.5707899 | C79: =C77/C78 -> 8.1953525 | D79: =D77/D78 -> 10.431344
A80: Upside / (Downside) | B80: =B79/DCF!$B$65-1 -> -0.54527405 | C80: =C79/DCF!$B$65-1 -> -0.43284758 | D80: =D79/DCF!$B$65-1 -> -0.27810766
A82: Base Case Reconciliation | B82: =C79-DCF!$B$64 -> 0

Sheet Power_Pivot_Analysis
A3: Row Labels | B3: Revenue | C3: Operating Profit | D3: Operating Margin | G3: FY2025 REVENUE GROWTH
A4: FY2024 | B4: 18909 | C4: 2906 | D4: 0.15368343 | G4: 0.12152943
A5: FY2025 | B5: 21207 | C5: 4468 | D5: 0.21068515
G7: Operating Profit Growth
G8: 0.5375086

Sheet Checks
A1: ROLLS-ROYCE MODEL CHECKS
A3: MODEL INTEGRITY CHECKS
A5: Check | B5: Difference/Result | C5: Status
A6: Forecast Revenue Reconcilliation | B6: =MAX(MAX(Forecast_Model!C32:G32),-MIN(Forecast_Model!C32:G32)) -> 0 | C6: =IF(ABS(B6)<0.01,"PASS","FAIL") -> PASS
A7: Forecast Operating Profit Reconciliation | B7: =MAX(MAX(Forecast_Model!C33:G33),-MIN(Forecast_Model!C33:G33)) -> 0 | C7: =IF(ABS(B7)<0.01,"PASS","FAIL") -> PASS
A8: WACC Capital Structure Weights | B8: =DCF!B24+DCF!B25-1 -> 0 | C8: =IF(ABS(B8)<0.0001,"PASS","FAIL") -> PASS
A9: DCF Enterprise Value Reconciliation | B9: =DCF!B60-(SUM(DCF!B48:F48)+DCF!B57) -> 0 | C9: =IF(ABS(B9)<0.01,"PASS","FAIL") -> PASS
A10: DCF Equity Value Reconciliation | B10: =DCF!B62-(DCF!B60+DCF!B61) -> 0 | C10: =IF(ABS(B10)<0.01,"PASS","FAIL") -> PASS
A11: DCF Per-Share Value Reconciliation | B11: =DCF!B64-(DCF!B62/DCF!B63) -> 0 | C11: =IF(ABS(B11)<0.0001,"PASS","FAIL") -> PASS
A12: WACC Greater Than Terminal Growth | B12: =DCF!B26-DCF!B27 -> 0.071193991 | C12: =IF(B12>0,"PASS","FAIL") -> PASS
A13: Sensitivity Base Case Reconciliation | B13: =Sensitivity!B5-DCF!B64 -> 0 | C13: =IF(ABS(B13)<0.01,"PASS","FAIL") -> PASS
A14: Scenario Base Case Reconciliation | B14: =Sensitivity!C82 -> 0 | C14: =IF(ABS(B14)<0.01,"PASS","FAIL") -> PASS
A15: Comps Market Cap Link | B15: =SUM(Comparable_Companies!D6:D11)-SUM(Comparable_Companies!R6:R11) -> 0 | C15: =IF(ABS(B15)<0.01,"PASS","FAIL") -> PASS
A16: Comps Enterprise Value Link | B16: =SUM(Comparable_Companies!E6:E11)-SUM(Comparable_Companies!S6:S11) -> 0 | C16: =IF(ABS(B16)<0.01,"PASS","FAIL") -> PASS
A17: Rolls-Royce Net Cash Consistency | B17: =Comparable_Companies!B32-DCF!B61 -> 0 | C17: =IF(ABS(B17)<0.01,"PASS","FAIL") -> PASS
A18: Historical Segment Revenue Reconciliation | B18: {=MAX(ABS(Historical_FS!B42:K42-(Historical_FS!B37:K37+Historical_FS!B38:K38+Historical_FS!B39:K39+Historical_FS!B40:K40+Historical_FS!B41:K41)))} -> 0 | C18: =IF(ABS(B18)<0.01,"PASS","REVIEW") -> PASS
A20: OVERALL MODEL STATUS | B20: =COUNTIF(C6:C18,"FAIL") -> 0 | C20: =IF(B20=0,"PASS","FAIL") -> PASS

Sheet Sources
A1: Financial Year | B1: Document Type | C1: File Name | D1: Primary Use | E1: Status | F1: Notes
A2: 2016 | B2: Annual Report | C2: RR_Annual_Report_2016.pdf | D2: Audited historical financial statements | E2: Downloaded | F2: Year ended 31 December 2016
A3: 2017 | B3: Annual Report | C3: RR_Annual_Report_2017.pdf | D3: Audited historical financial statements | E3: Downloaded | F3: Year ended 31 December 2017
A4: 2018 | B4: Annual Report | C4: RR_Annual_Report_2018.pdf | D4: Audited historical financial statements | E4: Downloaded | F4: Year ended 31 December 2018
A5: 2019 | B5: Annual Report | C5: RR_Annual_Report_2019.pdf | D5: Audited historical financial statements | E5: Downloaded | F5: Year ended 31 December 2019
A6: 2020 | B6: Annual Report | C6: RR_Annual_Report_2020.pdf | D6: Audited historical financial statements | E6: Downloaded | F6: Year ended 31 December 2020
A7: 2021 | B7: Annual Report | C7: RR_Annual_Report_2021.pdf | D7: Audited historical financial statements | E7: Downloaded | F7: Year ended 31 December 2021
A8: 2022 | B8: Annual Report | C8: RR_Annual_Report_2022.pdf | D8: Audited historical financial statements | E8: Downloaded | F8: Year ended 31 December 2022
A9: 2023 | B9: Annual Report | C9: RR_Annual_Report_2023.pdf | D9: Audited historical financial statements | E9: Downloaded | F9: Year ended 31 December 2023
A10: 2024 | B10: Annual Report | C10: RR_Annual_Report_2024.pdf | D10: Audited historical financial statements | E10: Downloaded | F10: Year ended 31 December 2024
A11: 2025 | B11: Full Year Results | C11: RR_FY2025_Results.pdf | D11: Headline underlying and statutory results | E11: Downloaded | F11: Year ended 31 December 2025
A14: ADDITIONAL MODEL & MARKET DATA SOURCES
A15: Source ID | B15: Category | C15: Source | D15: Period / Date | E15: Primary Use | F15: Reference
A16: S01 | B16: Company Results | C16: Rolls-Royce H1 2026 Results | D16: 46203 | E16: H1 revenue, operating profit, FCF, net cash, segment results and FY2026 guidance | F16: Rolls-Royce Investor Relations
A17: S02 | B17: Power Query | C17: Rolls-Royce FY2025 Full-Year Results Web Page | D17: FY2025 / FY2024 | E17: Automated statutory income statement, balance sheet and cash flow extraction | F17: Rolls-Royce Investor Relations
A18: S03 | B18: Regulatory Data | C18: Companies House Filing History API | D18: Historical | E18: Automated filing history and document metadata | F18: Company No. 07524813
A19: S04 | B19: Market Data | C19: Rolls-Royce Historical Share Price | D19: 30 Jun 2026 | E19: £14.45 DCF reference share price | F19: Historical market price source
A20: S05 | B20: Market Data | C20: UK 10-Year Government Bond Yield | D20: 30 Jun 2026 | E20: 4.83% risk-free rate | F20: Government bond market data
A21: S06 | B21: Valuation Input | C21: Equity Risk Premium | D21: Valuation Date | E21: 4.17% ERP used in cost of equity | F21: Valuation assumption
A22: S07 | B22: Comparable Companies | C22: Peer Company Market & Financial Data | D22: FY2025 / 30 Jun 2026 | E22: GE Aerospace, Safran, RTX, MTU Aero Engines and BAE Systems | F22: Company filings / historical market data
A25: MODEL METHODOLOGY
A26: M01 | B26: DCF | C26: Discounted Cash Flow Valuation | D26: FY2026E–FY2030E | E26: UFCF discounted using WACC with Gordon Growth terminal value | F26: DCF sheet
A27: M02 | B27: Trading Comps | C27: Comparable Companies Valuation | D27: FY2025 | E27: EV / Revenue and EV / EBIT peer multiples | F27: Comparable_Companies sheet
A28: M03 | B28: Scenario Analysis | C28: Bear / Base / Bull Valuation | D28: Forecast Period | E28: Revenue, margin, WACC and terminal-growth scenario analysis | F28: Sensitivity sheet
A29: M04 | B29: Sensitivity | C29: DCF WACC / Terminal Growth Data Table | D29: Valuation Date | E29: Two-variable valuation sensitivity | F29: Sensitivity sheet

Sheet Raw_Data
A1: Filing Date | B1: Description | C1: Type | D1: Transaction ID | E1: Pages | F1: Document Metadata URL | H1: Filing Date | I1: Description | J1: Type | K1: Transaction ID | L1: Pages | M1: Document Metadata URL | N1: Document ID | O1: Available Content Types | P1: PDF Available | Q1: XHTML Available | R1: XML Available | S1: JSON Available | U1: Financial Statement Line | V1: FY2025 | W1: FY2024 | Y1: Financial Statement Line | Z1: FY2025 | AA1: FY2024 | AC1: Financial Statement Line | AD1: FY2025 | AE1: FY2024 | AG1: STANDARDISED FINANCIAL STATEMENT MAPPING
A2: 46160 | B2: accounts-with-accounts-type-group | C2: AA | D2: MzUyMjI0MjIwOGFkaXF6a2N4 | E2: 219 | F2: https://document-api.company-information.service.gov.uk/document/290Q5B-syFwHjOrC0QjgmMAAfVgDHxEfsIuWAOXgjqU | H2: 46160 | I2: accounts-with-accounts-type-group | J2: AA | K2: MzUyMjI0MjIwOGFkaXF6a2N4 | L2: 219 | M2: https://document-api.company-information.service.gov.uk/document/290Q5B-syFwHjOrC0QjgmMAAfVgDHxEfsIuWAOXgjqU | N2: 290Q5B-syFwHjOrC0QjgmMAAfVgDHxEfsIuWAOXgjqU | O2: application/pdf | P2: TRUE | Q2: FALSE | R2: FALSE | S2: FALSE | U2: Revenue | V2: 21207 | W2: 18909 | Y2: ASSETS | AC2: Reconciliation of cash flows from operating activities
A3: 45874 | B3: accounts-with-accounts-type-interim | C3: AA | D3: MzQ3NTk0NzAyOWFkaXF6a2N4 | E3: 5 | F3: https://document-api.company-information.service.gov.uk/document/QdXJlhFCAD6T2HecXHegyaS3DP11B32l_X0qCZc-CEg | H3: 45874 | I3: accounts-with-accounts-type-interim | J3: AA | K3: MzQ3NTk0NzAyOWFkaXF6a2N4 | L3: 5 | M3: https://document-api.company-information.service.gov.uk/document/QdXJlhFCAD6T2HecXHegyaS3DP11B32l_X0qCZc-CEg | N3: QdXJlhFCAD6T2HecXHegyaS3DP11B32l_X0qCZc-CEg | O3: application/pdf | P3: TRUE | Q3: FALSE | R3: FALSE | S3: FALSE | U3: Cost of sales 1, 2 | V3: -15032 | W3: -14688 | Y3: Goodwill 1 | Z3: 1028 | AA3: 1009 | AC3: Operating profit | AD3: 4468 | AE3: 2906 | AG3: Statement | AH3: Standard Metric | AI3: Source Match Text | AJ3: FY2025 | AK3: FY2024 | AL3: Model Destination
A4: 45805 | B4: accounts-with-accounts-type-group | C4: AA | D4: MzQ2ODEyNzY4OGFkaXF6a2N4 | E4: 227 | F4: https://document-api.company-information.service.gov.uk/document/72hnZAT_ppnmu0QqusJ5Bt_pceo_eRbw0GRv0UnE4Lo | H4: 45805 | I4: accounts-with-accounts-type-group | J4: AA | K4: MzQ2ODEyNzY4OGFkaXF6a2N4 | L4: 227 | M4: https://document-api.company-information.service.gov.uk/document/72hnZAT_ppnmu0QqusJ5Bt_pceo_eRbw0GRv0UnE4Lo | N4: 72hnZAT_ppnmu0QqusJ5Bt_pceo_eRbw0GRv0UnE4Lo | O4: application/pdf | P4: TRUE | Q4: FALSE | R4: FALSE | S4: FALSE | U4: Gross profit | V4: 6175 | W4: 4221 | Y4: Intangible assets 1 | Z4: 3570 | AA4: 3393 | AC4: Loss on disposal of property, plant and equipment | AD4: 18 | AE4: 32 | AG4: Income Statement | AH4: Reported Revenue | AI4: Revenue | AJ4: =_xlfn.XLOOKUP("*"&$AI4&"*",$U$2:$U$100,$V$2:$V$100,"",2) -> 21207 | AK4: =_xlfn.XLOOKUP("*"&$AI4&"*",$U$2:$U$100,$W$2:$W$100,"",2) -> 18909 | AL4: Historical_FS!J8:K8
A5: 45446 | B5: accounts-with-accounts-type-group | C5: AA | D5: MzQyNDAyMzA3NWFkaXF6a2N4 | E5: 226 | F5: https://document-api.company-information.service.gov.uk/document/3_4-ebq6mZMDFYWf4-ds_JAcHFCgn1_TSjmlFtlZMAk | H5: 45446 | I5: accounts-with-accounts-type-group | J5: AA | K5: MzQyNDAyMzA3NWFkaXF6a2N4 | L5: 226 | M5: https://document-api.company-information.service.gov.uk/document/3_4-ebq6mZMDFYWf4-ds_JAcHFCgn1_TSjmlFtlZMAk | N5: 3_4-ebq6mZMDFYWf4-ds_JAcHFCgn1_TSjmlFtlZMAk | O5: application/pdf | P5: TRUE | Q5: FALSE | R5: FALSE | S5: FALSE | U5: Commercial and administrative costs | V5: -1268 | W5: -1284 | Y5: Property, plant and equipment | Z5: 4013 | AA5: 3724 | AC5: (Profit)/loss on disposal of intangible assets | AD5: -2 | AE5: 6 | AG5: Income Statement | AH5: Reported Operating Profit | AI5: Operating profit | AJ5: =_xlfn.XLOOKUP("*"&$AI5&"*",$U$2:$U$100,$V$2:$V$100,"",2) -> 4468 | AK5: =_xlfn.XLOOKUP("*"&$AI5&"*",$U$2:$U$100,$W$2:$W$100,"",2) -> 2906 | AL5: Historical_FS!J12:K12
A6: 45082 | B6: accounts-with-accounts-type-group | C6: AA | D6: MzM4MDk4NTQzNmFkaXF6a2N4 | E6: 216 | F6: https://document-api.company-information.service.gov.uk/document/O_EGT67idS0v18_lZom9ogdBnC2s0jThMe67ObbCUm8 | H6: 45082 | I6: accounts-with-accounts-type-group | J6: AA | K6: MzM4MDk4NTQzNmFkaXF6a2N4 | L6: 216 | M6: https://document-api.company-information.service.gov.uk/document/O_EGT67idS0v18_lZom9ogdBnC2s0jThMe67ObbCUm8 | N6: O_EGT67idS0v18_lZom9ogdBnC2s0jThMe67ObbCUm8 | O6: application/pdf | P6: TRUE | Q6: FALSE | R6: FALSE | S6: FALSE | U6: Research and development costs 2 | V6: -495 | W6: -203 | Y6: Right-of-use assets | Z6: 759 | AA6: 761 | AC6: Share of results of joint ventures and associates | AD6: -56 | AE6: -172 | AG6: Income Statement | AH6: Gain / (Loss) on Disposal of Businesses | AI6: Gain arising on disposal of businesses | AJ6: =_xlfn.XLOOKUP("*"&$AI6&"*",$U$2:$U$100,$V$2:$V$100,"",2) -> 809 | AK6: =_xlfn.XLOOKUP("*"&$AI6&"*",$U$2:$U$100,$W$2:$W$100,"",2) -> 16 | AL6: Historical_FS!J13:K13
A7: 44733 | B7: accounts-with-accounts-type-group | C7: AA | D7: MzM0MzE0MzA0NWFkaXF6a2N4 | E7: 225 | F7: https://document-api.company-information.service.gov.uk/document/7LSEKyocjBYqV865FgqZBB72elBIGDt0lXP4K4UhAC8 | H7: 44733 | I7: accounts-with-accounts-type-group | J7: AA | K7: MzM0MzE0MzA0NWFkaXF6a2N4 | L7: 225 | M7: https://document-api.company-information.service.gov.uk/document/7LSEKyocjBYqV865FgqZBB72elBIGDt0lXP4K4UhAC8 | N7: 7LSEKyocjBYqV865FgqZBB72elBIGDt0lXP4K4UhAC8 | O7: application/pdf | P7: TRUE | Q7: FALSE | R7: FALSE | S7: FALSE | U7: Share of results of joint ventures and associates | V7: 56 | W7: 172 | Y7: Investments 2 | Z7: 1289 | AA7: 597 | AC7: Dividends received from joint ventures and associates | AD7: 88 | AE7: 77 | AG7: Income Statement | AH7: Net Financing Income / (Cost) | AI7: Net financing income/(costs) | AJ7: =_xlfn.XLOOKUP("*"&$AI7&"*",$U$2:$U$100,$V$2:$V$100,"",2) -> 1658 | AK7: =_xlfn.XLOOKUP("*"&$AI7&"*",$U$2:$U$100,$W$2:$W$100,"",2) -> -688 | AL7: Historical_FS!J15:K15
A8: 44344 | B8: accounts-with-accounts-type-group | C8: AA | D8: MzMwMTg2MjMzNWFkaXF6a2N4 | E8: 215 | F8: https://document-api.company-information.service.gov.uk/document/agGIAlm2lS8YcZnrAXIy4kpybF0I8JDRtNuoBDKcSKA | H8: 44344 | I8: accounts-with-accounts-type-group | J8: AA | K8: MzMwMTg2MjMzNWFkaXF6a2N4 | L8: 215 | M8: https://document-api.company-information.service.gov.uk/document/agGIAlm2lS8YcZnrAXIy4kpybF0I8JDRtNuoBDKcSKA | N8: agGIAlm2lS8YcZnrAXIy4kpybF0I8JDRtNuoBDKcSKA | O8: application/pdf | P8: TRUE | Q8: FALSE | R8: FALSE | S8: FALSE | U8: Operating profit | V8: 4468 | W8: 2906 | Y8: Other financial assets | Z8: 523 | AA8: 126 | AC8: Impairment of goodwill | AE8: 13 | AG8: Income Statement | AH8: Profit Before Tax | AI8: Profit before taxation | AJ8: =_xlfn.XLOOKUP("*"&$AI8&"*",$U$2:$U$100,$V$2:$V$100,"",2) -> 6935 | AK8: =_xlfn.XLOOKUP("*"&$AI8&"*",$U$2:$U$100,$W$2:$W$100,"",2) -> 2234 | AL8: Historical_FS!J16:K16
A9: 44020 | B9: accounts-with-accounts-type-group | C9: AA | D9: MzI3MjQzMjUxOWFkaXF6a2N4 | E9: 214 | F9: https://document-api.company-information.service.gov.uk/document/Lo06G6Nh5M7GV1lDrJYR7bNNdpbB54rb-wqaboCGx0c | H9: 44020 | I9: accounts-with-accounts-type-group | J9: AA | K9: MzI3MjQzMjUxOWFkaXF6a2N4 | L9: 214 | M9: https://document-api.company-information.service.gov.uk/document/Lo06G6Nh5M7GV1lDrJYR7bNNdpbB54rb-wqaboCGx0c | N9: Lo06G6Nh5M7GV1lDrJYR7bNNdpbB54rb-wqaboCGx0c | O9: application/pdf | P9: TRUE | Q9: FALSE | R9: FALSE | S9: FALSE | U9: Gain arising on disposal of businesses 3 | V9: 809 | W9: 16 | Y9: Deferred tax assets | Z9: 3460 | AA9: 3660 | AC9: Amortisation and impairment of intangible assets | AD9: 241 | AE9: -133 | AG9: Income Statement | AH9: Taxation (Charge) / Credit | AI9: Taxation | AJ9: =_xlfn.XLOOKUP($AI9,$U$2:$U$100,$V$2:$V$100,"",0) -> -1099 | AK9: =_xlfn.XLOOKUP($AI9,$U$2:$U$100,$W$2:$W$100,"",0) -> 250 | AL9: Historical_FS!J17:K17
A10: 43607 | B10: accounts-with-accounts-type-group | C10: AA | D10: MzIzNTAyODA1N2FkaXF6a2N4 | E10: 210 | F10: https://document-api.company-information.service.gov.uk/document/GRgErn0BHOAPE-9Lb10WuRlZEqK8dMakqIHA3ERfij0 | H10: 43607 | I10: accounts-with-accounts-type-group | J10: AA | K10: MzIzNTAyODA1N2FkaXF6a2N4 | L10: 210 | M10: https://document-api.company-information.service.gov.uk/document/GRgErn0BHOAPE-9Lb10WuRlZEqK8dMakqIHA3ERfij0 | N10: GRgErn0BHOAPE-9Lb10WuRlZEqK8dMakqIHA3ERfij0 | O10: application/pdf | P10: TRUE | Q10: FALSE | R10: FALSE | S10: FALSE | U10: Profit before financing and taxation | V10: 5277 | W10: 2922 | Y10: Post-retirement scheme surpluses | Z10: 286 | AA10: 790 | AC10: Depreciation and impairment of property, plant and equipment | AD10: 338 | AE10: 400 | AG10: Income Statement | AH10: Net Income Attributable to Ordinary Shareholders | AI10: Ordinary shareholders | AJ10: =_xlfn.XLOOKUP("*"&$AI10&"*",$U$2:$U$100,$V$2:$V$100,"",2) -> 5841 | AK10: =_xlfn.XLOOKUP("*"&$AI10&"*",$U$2:$U$100,$W$2:$W$100,"",2) -> 2521 | AL10: Historical_FS!J19:K19
A11: 43238 | B11: accounts-amended-with-accounts-type-group | C11: AAMD | D11: MzIwNTE5MTg0OGFkaXF6a2N4 | E11: 209 | F11: https://document-api.company-information.service.gov.uk/document/TywIBuwm5kwmt9wdR0RDWR3rR6gEV2nWILnPFijapc4 | H11: 43238 | I11: accounts-amended-with-accounts-type-group | J11: AAMD | K11: MzIwNTE5MTg0OGFkaXF6a2N4 | L11: 209 | M11: https://document-api.company-information.service.gov.uk/document/TywIBuwm5kwmt9wdR0RDWR3rR6gEV2nWILnPFijapc4 | N11: TywIBuwm5kwmt9wdR0RDWR3rR6gEV2nWILnPFijapc4 | O11: application/pdf | P11: TRUE | Q11: FALSE | R11: FALSE | S11: FALSE | U11: Financing income | V11: 2137 | W11: 536 | Y11: Non-current assets | Z11: 14928 | AA11: 14060 | AC11: Depreciation and impairment of right-of-use assets | AD11: 158 | AE11: 265
A12: 43195 | B12: accounts-with-accounts-type-group | C12: AA | D12: MzIwMTg0OTgyMWFkaXF6a2N4 | E12: 208 | F12: https://document-api.company-information.service.gov.uk/document/1-GudCzAZceEvqtIzon7Jto32scEKT2qUhOqwZ7enxM | H12: 43195 | I12: accounts-with-accounts-type-group | J12: AA | K12: MzIwMTg0OTgyMWFkaXF6a2N4 | L12: 208 | M12: https://document-api.company-information.service.gov.uk/document/1-GudCzAZceEvqtIzon7Jto32scEKT2qUhOqwZ7enxM | N12: 1-GudCzAZceEvqtIzon7Jto32scEKT2qUhOqwZ7enxM | O12: application/pdf | P12: TRUE | Q12: FALSE | R12: FALSE | S12: FALSE | U12: Financing costs | V12: -479 | W12: -1224 | Y12: Inventories | Z12: 5728 | AA12: 5092 | AC12: Adjustment of amounts payable under residual value guarantees within lease liabilities | AE12: -6 | AG12: Balance Sheet | AH12: Cash and Cash Equivalents | AI12: Cash and cash equivalents | AJ12: =_xlfn.XLOOKUP("*"&$AI12&"*",$Y$2:$Y$100,$Z$2:$Z$100,"",2) -> 6244 | AK12: =_xlfn.XLOOKUP("*"&$AI12&"*",$Y$2:$Y$100,$AA$2:$AA$100,"",2) -> 5575 | AL12: Historical_FS!J31:K31
A13: 42867 | B13: accounts-with-accounts-type-group | C13: AA | D13: MzE3NTU2NjYwN2FkaXF6a2N4 | E13: 196 | F13: https://document-api.company-information.service.gov.uk/document/8NuWvPtR_MvQoXb03A_Nzsv621EvlsMw9fN1WzIFuZo | H13: 42867 | I13: accounts-with-accounts-type-group | J13: AA | K13: MzE3NTU2NjYwN2FkaXF6a2N4 | L13: 196 | M13: https://document-api.company-information.service.gov.uk/document/8NuWvPtR_MvQoXb03A_Nzsv621EvlsMw9fN1WzIFuZo | N13: 8NuWvPtR_MvQoXb03A_Nzsv621EvlsMw9fN1WzIFuZo | O13: application/pdf | P13: TRUE | Q13: FALSE | R13: FALSE | S13: FALSE | U13: Net financing income/(costs) 4 | V13: 1658 | W13: -688 | Y13: Trade receivables and other assets | Z13: 8946 | AA13: 8713 | AC13: Impairment of and other movements on investments | AE13: 4 | AG13: Balance Sheet | AH13: Total Assets | AI13: TOTAL ASSETS | AJ13: =_xlfn.XLOOKUP("*"&$AI13&"*",$Y$2:$Y$100,$Z$2:$Z$100,"",2) -> 38115 | AK13: =_xlfn.XLOOKUP("*"&$AI13&"*",$Y$2:$Y$100,$AA$2:$AA$100,"",2) -> 35686 | AL13: Ratio Analysis
A14: 42538 | B14: accounts-with-accounts-type-group | C14: AA | D14: MzE1MDYxNjM3NmFkaXF6a2N4 | E14: 188 | F14: https://document-api.company-information.service.gov.uk/document/75Qcvlk0Son15er3NHNOTDnnuwcROTWvsUOmgQFc-Jw | H14: 42538 | I14: accounts-with-accounts-type-group | J14: AA | K14: MzE1MDYxNjM3NmFkaXF6a2N4 | L14: 188 | M14: https://document-api.company-information.service.gov.uk/document/75Qcvlk0Son15er3NHNOTDnnuwcROTWvsUOmgQFc-Jw | N14: 75Qcvlk0Son15er3NHNOTDnnuwcROTWvsUOmgQFc-Jw | O14: application/pdf | P14: TRUE | Q14: FALSE | R14: FALSE | S14: FALSE | U14: Profit before taxation | V14: 6935 | W14: 2234 | Y14: Contract assets | Z14: 1897 | AA14: 1813 | AC14: Decrease in provisions | AD14: -486 | AE14: -56 | AG14: Balance Sheet | AH14: Current Assets | AI14: Current assets | AJ14: =_xlfn.XLOOKUP("*"&$AI14&"*",$Y$2:$Y$100,$Z$2:$Z$100,"",2) -> 14928 | AK14: =_xlfn.XLOOKUP("*"&$AI14&"*",$Y$2:$Y$100,$AA$2:$AA$100,"",2) -> 14060 | AL14: Ratio Analysis
A15: 42158 | B15: accounts-with-accounts-type-group | C15: AA | D15: MzEyNDQ0Njc4MmFkaXF6a2N4 | E15: 172 | F15: https://document-api.company-information.service.gov.uk/document/HPtj1EXKELOTJ7BHgb-zFZz4m1cLp86nS-PXsSXIGFs | H15: 42158 | I15: accounts-with-accounts-type-group | J15: AA | K15: MzEyNDQ0Njc4MmFkaXF6a2N4 | L15: 172 | M15: https://document-api.company-information.service.gov.uk/document/HPtj1EXKELOTJ7BHgb-zFZz4m1cLp86nS-PXsSXIGFs | N15: HPtj1EXKELOTJ7BHgb-zFZz4m1cLp86nS-PXsSXIGFs | O15: application/pdf | P15: TRUE | Q15: FALSE | R15: FALSE | S15: FALSE | U15: Taxation | V15: -1099 | W15: 250 | Y15: Taxation recoverable | Z15: 75 | AA15: 71 | AC15: Increase in inventories | AD15: -685 | AE15: -323 | AG15: Balance Sheet | AH15: Current Liabilities | AI15: Current liabilities | AJ15: =_xlfn.XLOOKUP("*"&$AI15&"*",$Y$2:$Y$100,$Z$2:$Z$100,"",2) -> -19287 | AK15: =_xlfn.XLOOKUP("*"&$AI15&"*",$Y$2:$Y$100,$AA$2:$AA$100,"",2) -> -16763 | AL15: Ratio Analysis
A16: 41761 | B16: accounts-with-accounts-type-group | C16: AA | D16: MzA5OTMyNTc5OWFkaXF6a2N4 | E16: 144 | F16: https://document-api.company-information.service.gov.uk/document/JeEfv13Oi7XV-yye4O3I0_h3eE6srbzioySbAp3gp2g | H16: 41761 | I16: accounts-with-accounts-type-group | J16: AA | K16: MzA5OTMyNTc5OWFkaXF6a2N4 | L16: 144 | M16: https://document-api.company-information.service.gov.uk/document/JeEfv13Oi7XV-yye4O3I0_h3eE6srbzioySbAp3gp2g | N16: JeEfv13Oi7XV-yye4O3I0_h3eE6srbzioySbAp3gp2g | O16: application/pdf | P16: TRUE | Q16: FALSE | R16: FALSE | S16: FALSE | U16: Profit for the year | V16: 5836 | W16: 2484 | Y16: Other financial assets | Z16: 282 | AA16: 209 | AC16: Movement in trade receivables/payables and other assets/liabilities | AD16: 763 | AE16: 833 | AG16: Balance Sheet | AH16: Total Liabilities | AI16: TOTAL LIABILITIES | AJ16: =_xlfn.XLOOKUP("*"&$AI16&"*",$Y$2:$Y$100,$Z$2:$Z$100,"",2) -> -35362 | AK16: =_xlfn.XLOOKUP("*"&$AI16&"*",$Y$2:$Y$100,$AA$2:$AA$100,"",2) -> -36567 | AL16: Ratio Analysis
A17: 41407 | B17: accounts-with-accounts-type-group | C17: AA | D17: MzA3Nzg4ODk0MGFkaXF6a2N4 | E17: 136 | F17: https://document-api.company-information.service.gov.uk/document/enPFg5cubYmn8l7e4iF5F7VvfVfq8_zCaQk9Mf8bebQ | H17: 41407 | I17: accounts-with-accounts-type-group | J17: AA | K17: MzA3Nzg4ODk0MGFkaXF6a2N4 | L17: 136 | M17: https://document-api.company-information.service.gov.uk/document/enPFg5cubYmn8l7e4iF5F7VvfVfq8_zCaQk9Mf8bebQ | N17: enPFg5cubYmn8l7e4iF5F7VvfVfq8_zCaQk9Mf8bebQ | O17: application/pdf | P17: TRUE | Q17: FALSE | R17: FALSE | S17: FALSE | U17: Attributable to: | Y17: Cash and cash equivalents | Z17: 6244 | AA17: 5575 | AC17: Movement in contract assets/liabilities | AD17: 704 | AE17: 752 | AG17: Balance Sheet | AH17: Net Assets | AI17: NET ASSETS | AJ17: =_xlfn.XLOOKUP("*"&$AI17&"*",$Y$2:$Y$100,$Z$2:$Z$100,"",2) -> 2753 | AK17: =_xlfn.XLOOKUP("*"&$AI17&"*",$Y$2:$Y$100,$AA$2:$AA$100,"",2) -> -881 | AL17: Ratio Analysis
A18: 41022 | B18: accounts-with-accounts-type-group | C18: AA | D18: MzA1NjI4MzkxMGFkaXF6a2N4 | E18: 134 | F18: https://document-api.company-information.service.gov.uk/document/vW3waOLKluD6_4uQyYzgN-eKArj05DkopCvDC6_ztdc | H18: 41022 | I18: accounts-with-accounts-type-group | J18: AA | K18: MzA1NjI4MzkxMGFkaXF6a2N4 | L18: 134 | M18: https://document-api.company-information.service.gov.uk/document/vW3waOLKluD6_4uQyYzgN-eKArj05DkopCvDC6_ztdc | N18: vW3waOLKluD6_4uQyYzgN-eKArj05DkopCvDC6_ztdc | O18: application/pdf | P18: TRUE | Q18: FALSE | R18: FALSE | S18: FALSE | U18: Ordinary shareholders | V18: 5841 | W18: 2521 | Y18: Current assets | Z18: 23172 | AA18: 21473 | AC18: Cash flows on other financial assets and liabilities held for operating purposes 1 | AD18: -578 | AE18: -676
A19: 40716 | B19: change-account-reference-date-company-current-shortened | C19: AA01 | D19: MzAzOTI2MTQzNWFkaXF6a2N4 | E19: 1 | F19: https://document-api.company-information.service.gov.uk/document/ukfHAHwpUHKjGLfxObzH6mCXMzmYXd9xm0sXWw45Kus | H19: 40716 | I19: change-account-reference-date-company-current-shortened | J19: AA01 | K19: MzAzOTI2MTQzNWFkaXF6a2N4 | L19: 1 | M19: https://document-api.company-information.service.gov.uk/document/ukfHAHwpUHKjGLfxObzH6mCXMzmYXd9xm0sXWw45Kus | N19: ukfHAHwpUHKjGLfxObzH6mCXMzmYXd9xm0sXWw45Kus | O19: application/pdf | P19: TRUE | Q19: FALSE | R19: FALSE | S19: FALSE | U19: Non-controlling interests (NCI) | V19: -5 | W19: -37 | Y19: Assets held for sale | Z19: 15 | AA19: 153 | AC19: Cash flows on settlement of excess derivative contracts 2 | AD19: -148 | AE19: -146
A20: 40610 | B20: accounts-balance-sheet | C20: BS | D20: MzAzMzQ1NDE0OGFkaXF6a2N4 | E20: 2 | F20: https://document-api.company-information.service.gov.uk/document/f0d6nLGIW5BCRuQ1ujXm6keZ7WQl89e_RQzUlSaW6hE | H20: 40610 | I20: accounts-balance-sheet | J20: BS | K20: MzAzMzQ1NDE0OGFkaXF6a2N4 | L20: 2 | M20: https://document-api.company-information.service.gov.uk/document/f0d6nLGIW5BCRuQ1ujXm6keZ7WQl89e_RQzUlSaW6hE | N20: f0d6nLGIW5BCRuQ1ujXm6keZ7WQl89e_RQzUlSaW6hE | O20: application/pdf | P20: TRUE | Q20: FALSE | R20: FALSE | S20: FALSE | U20: Profit for the year | V20: 5836 | W20: 2484 | Y20: TOTAL ASSETS | Z20: 38115 | AA20: 35686 | AC20: Interest received | AD20: 270 | AE20: 269
U21: Other comprehensive (expense)/income (OCI) | V21: -545 | W21: 50 | Y21: LIABILITIES | AC21: Net defined benefit post-retirement cost recognised in profit before financing | AD21: 42 | AE21: 56
U22: Total comprehensive income for the year | V22: 5291 | W22: 2534 | Y22: Borrowings and lease liabilities | Z22: -1426 | AA22: -1097 | AC22: Cash funding of defined benefit post-retirement schemes | AD22: -84 | AE22: -74
U23: Earnings per ordinary share attributable to ordinary shareholders: | Y23: Other financial liabilities | Z23: -293 | AA23: -642 | AC23: Share-based payments | AD23: 104 | AE23: 136
U24: Basic | Y24: Trade payables and other liabilities | Z24: -8863 | AA24: -8009 | AC24: Net cash inflow from operating activities before taxation | AD24: 5155 | AE24: 4163
U25: Diluted | Y25: Contract liabilities | Z25: -7832 | AA25: -6309 | AC25: Taxation paid | AD25: -590 | AE25: -381
Y26: Current tax liabilities | Z26: -366 | AA26: -117 | AC26: Net cash inflow from operating activities | AD26: 4565 | AE26: 3782
Y27: Provisions for liabilities and charges | Z27: -507 | AA27: -589 | AC27: Cash flows from investing activities
Y28: Current liabilities | Z28: -19287 | AA28: -16763 | AC28: Additions of intangible assets | AD28: -364 | AE28: -367
Y29: Borrowings and lease liabilities | Z29: -2846 | AA29: -4035 | AC29: Disposals of intangible assets | AD29: 5 | AE29: 5
Y30: Other financial liabilities | Z30: -627 | AA30: -1640 | AC30: Purchases of property, plant and equipment | AD30: -621 | AE30: -519
Y31: Trade payables and other liabilities | Z31: -1778 | AA31: -1965 | AC31: Disposals of property, plant and equipment | AD31: 2 | AE31: 5
Y32: Contract liabilities | Z32: -8762 | AA32: -9447 | AC32: Disposal of businesses (including cash flows on disposals in prior periods) | AD32: 80 | AE32: 62
Y33: Deferred tax liabilities | Z33: -101 | AA33: -231 | AC33: Movement in investments in joint ventures and associates | AD33: -41 | AE33: -17
Y34: Provisions for liabilities and charges | Z34: -1050 | AA34: -1405 | AC34: Net cash outflow from investing activities | AD34: -939 | AE34: -831
Y35: Post-retirement scheme deficits | Z35: -892 | AA35: -981 | AC35: Cash flows from financing activities
Y36: Non-current liabilities | Z36: -16056 | AA36: -19704 | AC36: Repayment of loans | AD36: -927 | AE36: -475
Y37: Liabilities associated with assets held for sale | Z37: -19 | AA37: -100 | AC37: Settlement of swaps hedging fixed rate borrowings | AD37: 93 | AE37: -11
Y38: TOTAL LIABILITIES | Z38: -35362 | AA38: -36567 | AC38: Proceeds from increase in loans | AD38: 177 | AE38: 7
Y39: NET ASSETS | Z39: 2753 | AA39: -881 | AC39: Capital element of lease payments | AD39: -232 | AE39: -299
Y40: EQUITY | AC40: Net cash flow from decrease in borrowings and lease liabilities | AD40: -889 | AE40: -778
Y41: Called-up share capital 3 | Z41: 1689 | AA41: 1701 | AC41: Interest paid | AD41: -180 | AE41: -200
Y42: Share premium 3 | AA42: 1012 | AC42: Interest element of lease payments | AD42: -74 | AE42: -83
Y43: Capital redemption reserve 3 | Z43: 5 | AA43: 168 | AC43: Fees paid on undrawn facilities | AD43: -8 | AE43: -15
Y44: Cash flow hedge reserve | Z44: 7 | AA44: 13 | AC44: Cash received on maturity of share-based payment schemes | AD44: 40
Y45: Translation reserve | Z45: 418 | AA45: 603 | AC45: Transactions with NCI 3 | AD45: 34 | AE45: 33
Y46: Retained earnings/(accumulated losses) | Z46: 607 | AA46: -4409 | AC46: Dividends to NCI | AD46: -1 | AE46: -3
Y47: Equity attributable to ordinary shareholders | Z47: 2726 | AA47: -912 | AC47: Redemption of C Shares | AD47: -2 | AE47: -1
Y48: Non-controlling interest (NCI) | Z48: 27 | AA48: 31 | AC48: Share buyback | AD48: -1008
Y49: TOTAL EQUITY | Z49: 2753 | AA49: -881 | AC49: Dividends paid | AD49: -885
AC50: Net cash outflow from financing activities | AD50: -2973 | AE50: -1047
AC51: Change in cash and cash equivalents | AD51: 653 | AE51: 1904
AC52: Cash and cash equivalents at 1 January | AD52: 5573 | AE52: 3731
AC53: Exchange gains/(losses) on cash and cash equivalents | AD53: 15 | AE53: -62
AC54: Cash and cash equivalents at 31 December 4 | AD54: 6241 | AE54: 5573
